Workbook

Sheet PORTADA
B5: VENDINS
B7: Plan de Negocio · Modelo Financiero · Análisis de Mercado · Neuquén Capital
B9: Diseñado por: | C9: Agustín Diez
B10: Proyecto: | C10: VENDINS — Máquinas Expendedoras
B11: Versión: | C11: 2.0 · TC maestro conectado a todas las hojas
B12: Fecha: | C12: Marzo 2026
B13: Moneda base: | C13: USD | ARS (fondo violeta = valor en pesos)
B14: Horizonte: | C14: 36 meses (3 años)
B16: ⚙ PARÁMETRO MAESTRO: Tipo de Cambio (SUPUESTOS!B4) — modificar solo esa celda para actualizar TODAS las proyecciones en ARS
B17: ÍNDICE DE HOJAS
B18: SUPUESTOS | C18: Todos los supuestos y parámetros del modelo (inputs AZUL). TC maestro en fila 4.
B19: COSTOS_IMPO | C19: Costo de importación: 2, 3 y 4 máquinas — China vs Italia — en USD y ARS
B20: FLUJO_CAJA | C20: Flujo de caja mensual 36 meses — 3 escenarios — USD y ARS (violeta)
B21: INDICADORES | C21: VAN, TIR, Payback — matriz de 9 escenarios — USD y ARS
B22: BREAK_EVEN | C22: Punto de equilibrio — ingresos mínimos en USD y ARS
B23: LEGAL | C23: Checklist regulatorio: AFIP, ARCA, DPR Neuquén, Municipal

Sheet SUPUESTOS
A1: VENDINS — SUPUESTOS DEL MODELO (v2.0)
A2: Parámetro | B2: Valor | C2: Fuente / Nota
A3: MACROECONÓMICOS
A4: ⚙ Tipo de cambio ARS / USD ← PARÁMETRO MAESTRO | B4: 1500 | C4: Cambiar SOLO aquí → se actualiza TODO el modelo (COSTOS_IMPO, FLUJO_CAJA, INDICADORES, BREAK_EVEN)
A5: Inflación anual estimada (%) | B5: 0.35 | C5: Proyección consenso
A6: Tasa de descuento anual — WACC proxy (%) | B6: 0.35 | C6: Alta por contexto Argentina
A7: Tasa de descuento mensual (WACC/12 equiv.) | B7: =(1+B6)^(1/12)-1 -> 0.025324057 | C7: (1+WACC)^(1/12)-1
A8: IVA alícuota general (%) | B8: 0.21 | C8: Argentina
A9: IMPORTACIÓN — NCM 8476
A10: Arancel AEC Mercosur NCM 8476 (%) | B10: 0.14 | C10: Decreto 513/2025 — verificar
A11: IVA importación (%) | B11: 0.21 | C11: Recuperable como crédito fiscal
A12: IVA adicional — percepción (%) | B12: 0.105 | C12: Recuperable como crédito fiscal
A13: Derecho estadístico (%) | B13: 0.005 | C13: Sobre valor CIF
A14: Despachante de aduana — honorarios (USD flat) | B14: 700 | C14: Estimación mercado
A15: Seguro marítimo (% sobre FOB) | B15: 0.015 | C15: Estándar mercado
A16: MÁQUINAS — PRECIOS FOB
A17: Precio FOB China — combo snack + bebidas (USD) | B17: 1800 | C17: Alibaba/Made-in-China: TCN, Xingyuan, AFEN
A18: Precio FOB Italia — FAS International (USD) | B18: 5500 | C18: Aurora Vending Argentina, distribuidor oficial
A19: Flete LCL China → Buenos Aires (USD, 2-4 máq.) | B19: 1200 | C19: Estimación LCL ~4-8 CBM
A20: Flete LCL Italia → Buenos Aires (USD, 2-4 máq.) | B20: 2200 | C20: Estimación LCL
A21: OPERACIÓN POR MÁQUINA / MES
A22: Ingresos brutos — Escenario PESIMISTA (USD) | B22: 300 | C22: Ubicación secundaria, baja rotación
A23: Ingresos brutos — Escenario BASE (USD) | B23: 600 | C23: Edificio corporativo / hospital
A24: Ingresos brutos — Escenario OPTIMISTA (USD) | B24: 1200 | C24: Petrolera / hospital alta rotación
A25: COGS — costo de producto (% de ingresos) | B25: 0.45 | C25: Margen bruto ~55% sobre retail
A26: Canon al locador (% de ingresos) | B26: 0.15 | C26: Rango mercado: 10-20%
A27: Ingresos Brutos Neuquén — alícuota (%) | B27: 0.02 | C27: DPR Neuquén Ley 3479 — microempresa
A28: Mantenimiento preventivo por máquina / mes (USD) | B28: 35 | C28: Repuestos + desplazamiento técnico
A29: Logística reposición por máquina / mes (USD) | B29: 25 | C29: Combustible + tiempo Agustín
A30: COSTOS FIJOS MENSUALES (USD)
A31: Contador / estudio contable | B31: 50 | C31: Tercerizado
A32: Seguro de equipos | B32: 30 | C32: Por flota completa
A33: Comunicaciones (teléfono, internet) | B33: 15
A34: Gastos varios / contingencia | B34: 20
A35: TOTAL COSTOS FIJOS MENSUALES (USD) | B35: =B30+B31+B32+B33 -> 95 | C35: Suma de fijos
A36: COSTOS ONE-TIME — CONSTITUCIÓN & LEGAL (USD)
A37: Constitución SRL (honorarios + aranceles) | B37: 950 | C37: Bconsultores.com.ar, ref. 2025
A38: Habilitación municipal Neuquén Capital | B38: 200 | C38: Programa Habilita Gratis → puede ser $0
A39: Asesoría legal inicial (contratos, reg.) | B39: 500 | C39: Honorarios abogado
A40: TOTAL COSTOS LEGALES ONE-TIME (USD) | B40: =B36+B37+B38 -> 1150
A41: CAPITAL DE TRABAJO INICIAL
A42: Stock inicial por máquina (USD) | B42: 300 | C42: Primer abastecimiento completo
A44: EQUIVALENCIAS EN PESOS (actualiza automáticamente con TC)
A45: Concepto (ARS) | B45: Valor en ARS | C45: Nota
A46: Revenue PESIMISTA / máq / mes (ARS) | B46: =B22*SUPUESTOS!$B$4 -> 450000 | C46: usd × TC (SUPUESTOS!B4)
A47: Revenue BASE / máq / mes (ARS) | B47: =B23*SUPUESTOS!$B$4 -> 900000 | C47: usd × TC (SUPUESTOS!B4)
A48: Revenue OPTIMISTA / máq / mes (ARS) | B48: =B24*SUPUESTOS!$B$4 -> 1800000 | C48: usd × TC (SUPUESTOS!B4)
A49: Costos fijos mensuales totales (ARS) | B49: =B35*SUPUESTOS!$B$4 -> 142500 | C49: usd × TC (SUPUESTOS!B4)
A50: Inversión inicial neta 3 máqs China (ARS) | B50: =(3*B17+B19+3*B17*B15+(3*B17+B19+3*B17*B15)*(1+B10)*B11+(3*B17+B19+3*B17*B15)*(1+B10)*B12+(3*B17+B19+3*B17*B15)*B13+B14-((3*B17+B19+3*B17*B15)*(1+B10))*(B11+B12)+B40+3*B42)*SUPUESTOS!$B$4 -> 14196608 | C50: usd × TC (SUPUESTOS!B4)
A51: Contribución neta / máq / mes — BASE (ARS) | B51: =(B23*(1-B25-B26-B27)-B28-B29)*SUPUESTOS!$B$4 -> 252000 | C51: usd × TC (SUPUESTOS!B4)
A52: CF Neto mensual — 3 máqs BASE (ARS) | B52: =(3*(B23*(1-B25-B26-B27)-B28-B29)-B35)*SUPUESTOS!$B$4 -> 613500 | C52: usd × TC (SUPUESTOS!B4)
A54: Nota: Texto AZUL = inputs modificables. Fondo VIOLETA = valor en ARS (TC maestro). Texto NEGRO = fórmulas USD.

Sheet COSTOS_IMPO
A1: VENDINS — COSTOS DE IMPORTACIÓN (USD + ARS según TC maestro)
C2: 2 MÁQUINAS | G2: 3 MÁQUINAS | K2: 4 MÁQUINAS
A3: Concepto | C3: China (USD) | D3: China (ARS) | E3: Italia (USD) | F3: Italia (ARS) | G3: China (USD) | H3: China (ARS) | I3: Italia (USD) | J3: Italia (ARS) | K3: China (USD) | L3: China (ARS) | M3: Italia (USD) | N3: Italia (ARS)
A4: ESCENARIO 2 MÁQUINAS
A5: Concepto | C5: China USD | D5: China ARS ×TC | E5: Italia USD | F5: Italia ARS ×TC
A6: FOB (USD) | C6: =2*SUPUESTOS!B17 -> 3600 | D6: =C6*SUPUESTOS!$B$4 -> 5400000 | E6: =2*SUPUESTOS!B18 -> 11000 | F6: =E6*SUPUESTOS!$B$4 -> 16500000
A7: Flete LCL (USD) | C7: =SUPUESTOS!B19 -> 1200 | D7: =C7*SUPUESTOS!$B$4 -> 1800000 | E7: =SUPUESTOS!B20 -> 2200 | F7: =E7*SUPUESTOS!$B$4 -> 3300000
A8: Seguro marítimo (USD) | C8: =2*SUPUESTOS!B17*SUPUESTOS!B15 -> 54 | D8: =C8*SUPUESTOS!$B$4 -> 81000 | E8: =2*SUPUESTOS!B18*SUPUESTOS!B15 -> 165 | F8: =E8*SUPUESTOS!$B$4 -> 247500
A9: Valor CIF (USD) | C9: =2*SUPUESTOS!B17+SUPUESTOS!B19+2*SUPUESTOS!B17*SUPUESTOS!B15 -> 4854 | D9: =C9*SUPUESTOS!$B$4 -> 7281000 | E9: =2*SUPUESTOS!B18+SUPUESTOS!B20+2*SUPUESTOS!B18*SUPUESTOS!B15 -> 13365 | F9: =E9*SUPUESTOS!$B$4 -> 20047500
A10: Arancel NCM 8476 (14%) | C10: =(2*SUPUESTOS!B17+SUPUESTOS!B19+2*SUPUESTOS!B17*SUPUESTOS!B15)*SUPUESTOS!B10 -> 679.56 | D10: =C10*SUPUESTOS!$B$4 -> 1019340 | E10: =(2*SUPUESTOS!B18+SUPUESTOS!B20+2*SUPUESTOS!B18*SUPUESTOS!B15)*SUPUESTOS!B10 -> 1871.1 | F10: =E10*SUPUESTOS!$B$4 -> 2806650
A11: IVA importación 21% — recuperable | C11: =(2*SUPUESTOS!B17+SUPUESTOS!B19+2*SUPUESTOS!B17*SUPUESTOS!B15)*(1+SUPUESTOS!B10)*SUPUESTOS!B11 -> 1162.0476 | D11: =C11*SUPUESTOS!$B$4 -> 1743071.4 | E11: =(2*SUPUESTOS!B18+SUPUESTOS!B20+2*SUPUESTOS!B18*SUPUESTOS!B15)*(1+SUPUESTOS!B10)*SUPUESTOS!B11 -> 3199.581 | F11: =E11*SUPUESTOS!$B$4 -> 4799371.5
A12: IVA adicional 10.5% — recuperable | C12: =(2*SUPUESTOS!B17+SUPUESTOS!B19+2*SUPUESTOS!B17*SUPUESTOS!B15)*(1+SUPUESTOS!B10)*SUPUESTOS!B12 -> 581.0238 | D12: =C12*SUPUESTOS!$B$4 -> 871535.7 | E12: =(2*SUPUESTOS!B18+SUPUESTOS!B20+2*SUPUESTOS!B18*SUPUESTOS!B15)*(1+SUPUESTOS!B10)*SUPUESTOS!B12 -> 1599.7905 | F12: =E12*SUPUESTOS!$B$4 -> 2399685.8
A13: Derecho estadístico 0.5% | C13: =(2*SUPUESTOS!B17+SUPUESTOS!B19+2*SUPUESTOS!B17*SUPUESTOS!B15)*SUPUESTOS!B13 -> 24.27 | D13: =C13*SUPUESTOS!$B$4 -> 36405 | E13: =(2*SUPUESTOS!B18+SUPUESTOS!B20+2*SUPUESTOS!B18*SUPUESTOS!B15)*SUPUESTOS!B13 -> 66.825 | F13: =E13*SUPUESTOS!$B$4 -> 100237.5
A14: Despachante de aduana (flat) | C14: =SUPUESTOS!B14 -> 700 | D14: =C14*SUPUESTOS!$B$4 -> 1050000 | E14: =SUPUESTOS!B14 -> 700 | F14: =E14*SUPUESTOS!$B$4 -> 1050000
A15: TOTAL DESEMBOLSO IMPORTACIÓN (USD) | C15: =2*SUPUESTOS!B17+SUPUESTOS!B19+2*SUPUESTOS!B17*SUPUESTOS!B15+(2*SUPUESTOS!B17+SUPUESTOS!B19+2*SUPUESTOS!B17*SUPUESTOS!B15)*SUPUESTOS!B10+(2*SUPUESTOS!B17+SUPUESTOS!B19+2*SUPUESTOS!B17*SUPUESTOS!B15)*(1+SUPUESTOS!B10)*SUPUESTOS!B11+(2*SUPUESTOS!B17+SUPUESTOS!B19+2*SUPUESTOS!B17*SUPUESTOS!B15)*(1+SUPUESTOS!B10)*SUPUESTOS!B12+(2*SUPUESTOS!B17+SUPUESTOS!B19+2*SUPUESTOS!B17*SUPUESTOS!B15)*SUPUESTOS!B13+SUPUESTOS!B14 -> 8000.9014 | D15: =C15*SUPUESTOS!$B$4 -> 12001352 | E15: =2*SUPUESTOS!B18+SUPUESTOS!B20+2*SUPUESTOS!B18*SUPUESTOS!B15+(2*SUPUESTOS!B18+SUPUESTOS!B20+2*SUPUESTOS!B18*SUPUESTOS!B15)*SUPUESTOS!B10+(2*SUPUESTOS!B18+SUPUESTOS!B20+2*SUPUESTOS!B18*SUPUESTOS!B15)*(1+SUPUESTOS!B10)*SUPUESTOS!B11+(2*SUPUESTOS!B18+SUPUESTOS!B20+2*SUPUESTOS!B18*SUPUESTOS!B15)*(1+SUPUESTOS!B10)*SUPUESTOS!B12+(2*SUPUESTOS!B18+SUPUESTOS!B20+2*SUPUESTOS!B18*SUPUESTOS!B15)*SUPUESTOS!B13+SUPUESTOS!B14 -> 20802.297 | F15: =E15*SUPUESTOS!$B$4 -> 31203445
A16: (−) IVA recuperable (crédito fiscal) | C16: =(2*SUPUESTOS!B17+SUPUESTOS!B19+2*SUPUESTOS!B17*SUPUESTOS!B15)*(1+SUPUESTOS!B10)*(SUPUESTOS!B11+SUPUESTOS!B12) -> 1743.0714 | D16: =C16*SUPUESTOS!$B$4 -> 2614607.1 | E16: =(2*SUPUESTOS!B18+SUPUESTOS!B20+2*SUPUESTOS!B18*SUPUESTOS!B15)*(1+SUPUESTOS!B10)*(SUPUESTOS!B11+SUPUESTOS!B12) -> 4799.3715 | F16: =E16*SUPUESTOS!$B$4 -> 7199057.2
A17: (+) Constitución legal SRL + habilitaciones | C17: =SUPUESTOS!$B$40 -> 1150 | D17: =C17*SUPUESTOS!$B$4 -> 1725000 | E17: =SUPUESTOS!$B$40 -> 1150 | F17: =E17*SUPUESTOS!$B$4 -> 1725000
A18: (+) Capital de trabajo inicial (2 × stock) | C18: =2*SUPUESTOS!$B$42 -> 600 | D18: =C18*SUPUESTOS!$B$4 -> 900000 | E18: =2*SUPUESTOS!$B$42 -> 600 | F18: =E18*SUPUESTOS!$B$4 -> 900000
A19: INVERSIÓN INICIAL NETA (sin IVA recuperable) | C19: =2*SUPUESTOS!B17+SUPUESTOS!B19+2*SUPUESTOS!B17*SUPUESTOS!B15+(2*SUPUESTOS!B17+SUPUESTOS!B19+2*SUPUESTOS!B17*SUPUESTOS!B15)*SUPUESTOS!B10+(2*SUPUESTOS!B17+SUPUESTOS!B19+2*SUPUESTOS!B17*SUPUESTOS!B15)*(1+SUPUESTOS!B10)*SUPUESTOS!B11+(2*SUPUESTOS!B17+SUPUESTOS!B19+2*SUPUESTOS!B17*SUPUESTOS!B15)*(1+SUPUESTOS!B10)*SUPUESTOS!B12+(2*SUPUESTOS!B17+SUPUESTOS!B19+2*SUPUESTOS!B17*SUPUESTOS!B15)*SUPUESTOS!B13+SUPUESTOS!B14-((2*SUPUESTOS!B17+SUPUESTOS!B19+2*SUPUESTOS!B17*SUPUESTOS!B15)*(1+SUPUESTOS!B10)*(SUPUESTOS!B11+SUPUESTOS!B12))+SUPUESTOS!$B$40+2*SUPUESTOS!$B$42 -> 8007.83 | D19: =C19*SUPUESTOS!$B$4 -> 12011745 | E19: =2*SUPUESTOS!B18+SUPUESTOS!B20+2*SUPUESTOS!B18*SUPUESTOS!B15+(2*SUPUESTOS!B18+SUPUESTOS!B20+2*SUPUESTOS!B18*SUPUESTOS!B15)*SUPUESTOS!B10+(2*SUPUESTOS!B18+SUPUESTOS!B20+2*SUPUESTOS!B18*SUPUESTOS!B15)*(1+SUPUESTOS!B10)*SUPUESTOS!B11+(2*SUPUESTOS!B18+SUPUESTOS!B20+2*SUPUESTOS!B18*SUPUESTOS!B15)*(1+SUPUESTOS!B10)*SUPUESTOS!B12+(2*SUPUESTOS!B18+SUPUESTOS!B20+2*SUPUESTOS!B18*SUPUESTOS!B15)*SUPUESTOS!B13+SUPUESTOS!B14-((2*SUPUESTOS!B18+SUPUESTOS!B20+2*SUPUESTOS!B18*SUPUESTOS!B15)*(1+SUPUESTOS!B10)*(SUPUESTOS!B11+SUPUESTOS!B12))+SUPUESTOS!$B$40+2*SUPUESTOS!$B$42 -> 17752.925 | F19: =E19*SUPUESTOS!$B$4 -> 26629388
A20: Costo promedio por máquina — neto (USD) | C20: =C19/2 -> 4003.915 | D20: =C20*SUPUESTOS!$B$4 -> 6005872.5 | E20: =E19/2 -> 8876.4625 | F20: =E20*SUPUESTOS!$B$4 -> 13314694
A22: ESCENARIO 3 MÁQUINAS
A23: Concepto | G23: China USD | H23: China ARS ×TC | I23: Italia USD | J23: Italia ARS ×TC
A24: FOB (USD) | G24: =3*SUPUESTOS!B17 -> 5400 | H24: =G24*SUPUESTOS!$B$4 -> 8100000 | I24: =3*SUPUESTOS!B18 -> 16500 | J24: =I24*SUPUESTOS!$B$4 -> 24750000
A25: Flete LCL (USD) | G25: =SUPUESTOS!B19 -> 1200 | H25: =G25*SUPUESTOS!$B$4 -> 1800000 | I25: =SUPUESTOS!B20 -> 2200 | J25: =I25*SUPUESTOS!$B$4 -> 3300000
A26: Seguro marítimo (USD) | G26: =3*SUPUESTOS!B17*SUPUESTOS!B15 -> 81 | H26: =G26*SUPUESTOS!$B$4 -> 121500 | I26: =3*SUPUESTOS!B18*SUPUESTOS!B15 -> 247.5 | J26: =I26*SUPUESTOS!$B$4 -> 371250
A27: Valor CIF (USD) | G27: =3*SUPUESTOS!B17+SUPUESTOS!B19+3*SUPUESTOS!B17*SUPUESTOS!B15 -> 6681 | H27: =G27*SUPUESTOS!$B$4 -> 10021500 | I27: =3*SUPUESTOS!B18+SUPUESTOS!B20+3*SUPUESTOS!B18*SUPUESTOS!B15 -> 18947.5 | J27: =I27*SUPUESTOS!$B$4 -> 28421250
A28: Arancel NCM 8476 (14%) | G28: =(3*SUPUESTOS!B17+SUPUESTOS!B19+3*SUPUESTOS!B17*SUPUESTOS!B15)*SUPUESTOS!B10 -> 935.34 | H28: =G28*SUPUESTOS!$B$4 -> 1403010 | I28: =(3*SUPUESTOS!B18+SUPUESTOS!B20+3*SUPUESTOS!B18*SUPUESTOS!B15)*SUPUESTOS!B10 -> 2652.65 | J28: =I28*SUPUESTOS!$B$4 -> 3978975
A29: IVA importación 21% — recuperable | G29: =(3*SUPUESTOS!B17+SUPUESTOS!B19+3*SUPUESTOS!B17*SUPUESTOS!B15)*(1+SUPUESTOS!B10)*SUPUESTOS!B11 -> 1599.4314 | H29: =G29*SUPUESTOS!$B$4 -> 2399147.1 | I29: =(3*SUPUESTOS!B18+SUPUESTOS!B20+3*SUPUESTOS!B18*SUPUESTOS!B15)*(1+SUPUESTOS!B10)*SUPUESTOS!B11 -> 4536.0315 | J29: =I29*SUPUESTOS!$B$4 -> 6804047.2
A30: IVA adicional 10.5% — recuperable | G30: =(3*SUPUESTOS!B17+SUPUESTOS!B19+3*SUPUESTOS!B17*SUPUESTOS!B15)*(1+SUPUESTOS!B10)*SUPUESTOS!B12 -> 799.7157 | H30: =G30*SUPUESTOS!$B$4 -> 1199573.6 | I30: =(3*SUPUESTOS!B18+SUPUESTOS!B20+3*SUPUESTOS!B18*SUPUESTOS!B15)*(1+SUPUESTOS!B10)*SUPUESTOS!B12 -> 2268.0158 | J30: =I30*SUPUESTOS!$B$4 -> 3402023.6
A31: Derecho estadístico 0.5% | G31: =(3*SUPUESTOS!B17+SUPUESTOS!B19+3*SUPUESTOS!B17*SUPUESTOS!B15)*SUPUESTOS!B13 -> 33.405 | H31: =G31*SUPUESTOS!$B$4 -> 50107.5 | I31: =(3*SUPUESTOS!B18+SUPUESTOS!B20+3*SUPUESTOS!B18*SUPUESTOS!B15)*SUPUESTOS!B13 -> 94.7375 | J31: =I31*SUPUESTOS!$B$4 -> 142106.25
A32: Despachante de aduana (flat) | G32: =SUPUESTOS!B14 -> 700 | H32: =G32*SUPUESTOS!$B$4 -> 1050000 | I32: =SUPUESTOS!B14 -> 700 | J32: =I32*SUPUESTOS!$B$4 -> 1050000
A33: TOTAL DESEMBOLSO IMPORTACIÓN (USD) | G33: =3*SUPUESTOS!B17+SUPUESTOS!B19+3*SUPUESTOS!B17*SUPUESTOS!B15+(3*SUPUESTOS!B17+SUPUESTOS!B19+3*SUPUESTOS!B17*SUPUESTOS!B15)*SUPUESTOS!B10+(3*SUPUESTOS!B17+SUPUESTOS!B19+3*SUPUESTOS!B17*SUPUESTOS!B15)*(1+SUPUESTOS!B10)*SUPUESTOS!B11+(3*SUPUESTOS!B17+SUPUESTOS!B19+3*SUPUESTOS!B17*SUPUESTOS!B15)*(1+SUPUESTOS!B10)*SUPUESTOS!B12+(3*SUPUESTOS!B17+SUPUESTOS!B19+3*SUPUESTOS!B17*SUPUESTOS!B15)*SUPUESTOS!B13+SUPUESTOS!B14 -> 10748.892 | H33: =G33*SUPUESTOS!$B$4 -> 16123338 | I33: =3*SUPUESTOS!B18+SUPUESTOS!B20+3*SUPUESTOS!B18*SUPUESTOS!B15+(3*SUPUESTOS!B18+SUPUESTOS!B20+3*SUPUESTOS!B18*SUPUESTOS!B15)*SUPUESTOS!B10+(3*SUPUESTOS!B18+SUPUESTOS!B20+3*SUPUESTOS!B18*SUPUESTOS!B15)*(1+SUPUESTOS!B10)*SUPUESTOS!B11+(3*SUPUESTOS!B18+SUPUESTOS!B20+3*SUPUESTOS!B18*SUPUESTOS!B15)*(1+SUPUESTOS!B10)*SUPUESTOS!B12+(3*SUPUESTOS!B18+SUPUESTOS!B20+3*SUPUESTOS!B18*SUPUESTOS!B15)*SUPUESTOS!B13+SUPUESTOS!B14 -> 29198.935 | J33: =I33*SUPUESTOS!$B$4 -> 43798402
A34: (−) IVA recuperable (crédito fiscal) | G34: =(3*SUPUESTOS!B17+SUPUESTOS!B19+3*SUPUESTOS!B17*SUPUESTOS!B15)*(1+SUPUESTOS!B10)*(SUPUESTOS!B11+SUPUESTOS!B12) -> 2399.1471 | H34: =G34*SUPUESTOS!$B$4 -> 3598720.6 | I34: =(3*SUPUESTOS!B18+SUPUESTOS!B20+3*SUPUESTOS!B18*SUPUESTOS!B15)*(1+SUPUESTOS!B10)*(SUPUESTOS!B11+SUPUESTOS!B12) -> 6804.0472 | J34: =I34*SUPUESTOS!$B$4 -> 10206071
A35: (+) Constitución legal SRL + habilitaciones | G35: =SUPUESTOS!$B$40 -> 1150 | H35: =G35*SUPUESTOS!$B$4 -> 1725000 | I35: =SUPUESTOS!$B$40 -> 1150 | J35: =I35*SUPUESTOS!$B$4 -> 1725000
A36: (+) Capital de trabajo inicial (3 × stock) | G36: =3*SUPUESTOS!$B$42 -> 900 | H36: =G36*SUPUESTOS!$B$4 -> 1350000 | I36: =3*SUPUESTOS!$B$42 -> 900 | J36: =I36*SUPUESTOS!$B$4 -> 1350000
A37: INVERSIÓN INICIAL NETA (sin IVA recuperable) | G37: =3*SUPUESTOS!B17+SUPUESTOS!B19+3*SUPUESTOS!B17*SUPUESTOS!B15+(3*SUPUESTOS!B17+SUPUESTOS!B19+3*SUPUESTOS!B17*SUPUESTOS!B15)*SUPUESTOS!B10+(3*SUPUESTOS!B17+SUPUESTOS!B19+3*SUPUESTOS!B17*SUPUESTOS!B15)*(1+SUPUESTOS!B10)*SUPUESTOS!B11+(3*SUPUESTOS!B17+SUPUESTOS!B19+3*SUPUESTOS!B17*SUPUESTOS!B15)*(1+SUPUESTOS!B10)*SUPUESTOS!B12+(3*SUPUESTOS!B17+SUPUESTOS!B19+3*SUPUESTOS!B17*SUPUESTOS!B15)*SUPUESTOS!B13+SUPUESTOS!B14-((3*SUPUESTOS!B17+SUPUESTOS!B19+3*SUPUESTOS!B17*SUPUESTOS!B15)*(1+SUPUESTOS!B10)*(SUPUESTOS!B11+SUPUESTOS!B12))+SUPUESTOS!$B$40+3*SUPUESTOS!$B$42 -> 10399.745 | H37: =G37*SUPUESTOS!$B$4 -> 15599618 | I37: =3*SUPUESTOS!B18+SUPUESTOS!B20+3*SUPUESTOS!B18*SUPUESTOS!B15+(3*SUPUESTOS!B18+SUPUESTOS!B20+3*SUPUESTOS!B18*SUPUESTOS!B15)*SUPUESTOS!B10+(3*SUPUESTOS!B18+SUPUESTOS!B20+3*SUPUESTOS!B18*SUPUESTOS!B15)*(1+SUPUESTOS!B10)*SUPUESTOS!B11+(3*SUPUESTOS!B18+SUPUESTOS!B20+3*SUPUESTOS!B18*SUPUESTOS!B15)*(1+SUPUESTOS!B10)*SUPUESTOS!B12+(3*SUPUESTOS!B18+SUPUESTOS!B20+3*SUPUESTOS!B18*SUPUESTOS!B15)*SUPUESTOS!B13+SUPUESTOS!B14-((3*SUPUESTOS!B18+SUPUESTOS!B20+3*SUPUESTOS!B18*SUPUESTOS!B15)*(1+SUPUESTOS!B10)*(SUPUESTOS!B11+SUPUESTOS!B12))+SUPUESTOS!$B$40+3*SUPUESTOS!$B$42 -> 24444.888 | J37: =I37*SUPUESTOS!$B$4 -> 36667331
A38: Costo promedio por máquina — neto (USD) | G38: =G37/3 -> 3466.5817 | H38: =G38*SUPUESTOS!$B$4 -> 5199872.5 | I38: =I37/3 -> 8148.2958 | J38: =I38*SUPUESTOS!$B$4 -> 12222444
A40: ESCENARIO 4 MÁQUINAS
A41: Concepto | K41: China USD | L41: China ARS ×TC | M41: Italia USD | N41: Italia ARS ×TC
A42: FOB (USD) | K42: =4*SUPUESTOS!B17 -> 7200 | L42: =K42*SUPUESTOS!$B$4 -> 10800000 | M42: =4*SUPUESTOS!B18 -> 22000 | N42: =M42*SUPUESTOS!$B$4 -> 33000000
A43: Flete LCL (USD) | K43: =SUPUESTOS!B19 -> 1200 | L43: =K43*SUPUESTOS!$B$4 -> 1800000 | M43: =SUPUESTOS!B20 -> 2200 | N43: =M43*SUPUESTOS!$B$4 -> 3300000
A44: Seguro marítimo (USD) | K44: =4*SUPUESTOS!B17*SUPUESTOS!B15 -> 108 | L44: =K44*SUPUESTOS!$B$4 -> 162000 | M44: =4*SUPUESTOS!B18*SUPUESTOS!B15 -> 330 | N44: =M44*SUPUESTOS!$B$4 -> 495000
A45: Valor CIF (USD) | K45: =4*SUPUESTOS!B17+SUPUESTOS!B19+4*SUPUESTOS!B17*SUPUESTOS!B15 -> 8508 | L45: =K45*SUPUESTOS!$B$4 -> 12762000 | M45: =4*SUPUESTOS!B18+SUPUESTOS!B20+4*SUPUESTOS!B18*SUPUESTOS!B15 -> 24530 | N45: =M45*SUPUESTOS!$B$4 -> 36795000
A46: Arancel NCM 8476 (14%) | K46: =(4*SUPUESTOS!B17+SUPUESTOS!B19+4*SUPUESTOS!B17*SUPUESTOS!B15)*SUPUESTOS!B10 -> 1191.12 | L46: =K46*SUPUESTOS!$B$4 -> 1786680 | M46: =(4*SUPUESTOS!B18+SUPUESTOS!B20+4*SUPUESTOS!B18*SUPUESTOS!B15)*SUPUESTOS!B10 -> 3434.2 | N46: =M46*SUPUESTOS!$B$4 -> 5151300
A47: IVA importación 21% — recuperable | K47: =(4*SUPUESTOS!B17+SUPUESTOS!B19+4*SUPUESTOS!B17*SUPUESTOS!B15)*(1+SUPUESTOS!B10)*SUPUESTOS!B11 -> 2036.8152 | L47: =K47*SUPUESTOS!$B$4 -> 3055222.8 | M47: =(4*SUPUESTOS!B18+SUPUESTOS!B20+4*SUPUESTOS!B18*SUPUESTOS!B15)*(1+SUPUESTOS!B10)*SUPUESTOS!B11 -> 5872.482 | N47: =M47*SUPUESTOS!$B$4 -> 8808723
A48: IVA adicional 10.5% — recuperable | K48: =(4*SUPUESTOS!B17+SUPUESTOS!B19+4*SUPUESTOS!B17*SUPUESTOS!B15)*(1+SUPUESTOS!B10)*SUPUESTOS!B12 -> 1018.4076 | L48: =K48*SUPUESTOS!$B$4 -> 1527611.4 | M48: =(4*SUPUESTOS!B18+SUPUESTOS!B20+4*SUPUESTOS!B18*SUPUESTOS!B15)*(1+SUPUESTOS!B10)*SUPUESTOS!B12 -> 2936.241 | N48: =M48*SUPUESTOS!$B$4 -> 4404361.5
A49: Derecho estadístico 0.5% | K49: =(4*SUPUESTOS!B17+SUPUESTOS!B19+4*SUPUESTOS!B17*SUPUESTOS!B15)*SUPUESTOS!B13 -> 42.54 | L49: =K49*SUPUESTOS!$B$4 -> 63810 | M49: =(4*SUPUESTOS!B18+SUPUESTOS!B20+4*SUPUESTOS!B18*SUPUESTOS!B15)*SUPUESTOS!B13 -> 122.65 | N49: =M49*SUPUESTOS!$B$4 -> 183975
A50: Despachante de aduana (flat) | K50: =SUPUESTOS!B14 -> 700 | L50: =K50*SUPUESTOS!$B$4 -> 1050000 | M50: =SUPUESTOS!B14 -> 700 | N50: =M50*SUPUESTOS!$B$4 -> 1050000
A51: TOTAL DESEMBOLSO IMPORTACIÓN (USD) | K51: =4*SUPUESTOS!B17+SUPUESTOS!B19+4*SUPUESTOS!B17*SUPUESTOS!B15+(4*SUPUESTOS!B17+SUPUESTOS!B19+4*SUPUESTOS!B17*SUPUESTOS!B15)*SUPUESTOS!B10+(4*SUPUESTOS!B17+SUPUESTOS!B19+4*SUPUESTOS!B17*SUPUESTOS!B15)*(1+SUPUESTOS!B10)*SUPUESTOS!B11+(4*SUPUESTOS!B17+SUPUESTOS!B19+4*SUPUESTOS!B17*SUPUESTOS!B15)*(1+SUPUESTOS!B10)*SUPUESTOS!B12+(4*SUPUESTOS!B17+SUPUESTOS!B19+4*SUPUESTOS!B17*SUPUESTOS!B15)*SUPUESTOS!B13+SUPUESTOS!B14 -> 13496.883 | L51: =K51*SUPUESTOS!$B$4 -> 20245324 | M51: =4*SUPUESTOS!B18+SUPUESTOS!B20+4*SUPUESTOS!B18*SUPUESTOS!B15+(4*SUPUESTOS!B18+SUPUESTOS!B20+4*SUPUESTOS!B18*SUPUESTOS!B15)*SUPUESTOS!B10+(4*SUPUESTOS!B18+SUPUESTOS!B20+4*SUPUESTOS!B18*SUPUESTOS!B15)*(1+SUPUESTOS!B10)*SUPUESTOS!B11+(4*SUPUESTOS!B18+SUPUESTOS!B20+4*SUPUESTOS!B18*SUPUESTOS!B15)*(1+SUPUESTOS!B10)*SUPUESTOS!B12+(4*SUPUESTOS!B18+SUPUESTOS!B20+4*SUPUESTOS!B18*SUPUESTOS!B15)*SUPUESTOS!B13+SUPUESTOS!B14 -> 37595.573 | N51: =M51*SUPUESTOS!$B$4 -> 56393360
A52: (−) IVA recuperable (crédito fiscal) | K52: =(4*SUPUESTOS!B17+SUPUESTOS!B19+4*SUPUESTOS!B17*SUPUESTOS!B15)*(1+SUPUESTOS!B10)*(SUPUESTOS!B11+SUPUESTOS!B12) -> 3055.2228 | L52: =K52*SUPUESTOS!$B$4 -> 4582834.2 | M52: =(4*SUPUESTOS!B18+SUPUESTOS!B20+4*SUPUESTOS!B18*SUPUESTOS!B15)*(1+SUPUESTOS!B10)*(SUPUESTOS!B11+SUPUESTOS!B12) -> 8808.723 | N52: =M52*SUPUESTOS!$B$4 -> 13213084
A53: (+) Constitución legal SRL + habilitaciones | K53: =SUPUESTOS!$B$40 -> 1150 | L53: =K53*SUPUESTOS!$B$4 -> 1725000 | M53: =SUPUESTOS!$B$40 -> 1150 | N53: =M53*SUPUESTOS!$B$4 -> 1725000
A54: (+) Capital de trabajo inicial (4 × stock) | K54: =4*SUPUESTOS!$B$42 -> 1200 | L54: =K54*SUPUESTOS!$B$4 -> 1800000 | M54: =4*SUPUESTOS!$B$42 -> 1200 | N54: =M54*SUPUESTOS!$B$4 -> 1800000
A55: INVERSIÓN INICIAL NETA (sin IVA recuperable) | K55: =4*SUPUESTOS!B17+SUPUESTOS!B19+4*SUPUESTOS!B17*SUPUESTOS!B15+(4*SUPUESTOS!B17+SUPUESTOS!B19+4*SUPUESTOS!B17*SUPUESTOS!B15)*SUPUESTOS!B10+(4*SUPUESTOS!B17+SUPUESTOS!B19+4*SUPUESTOS!B17*SUPUESTOS!B15)*(1+SUPUESTOS!B10)*SUPUESTOS!B11+(4*SUPUESTOS!B17+SUPUESTOS!B19+4*SUPUESTOS!B17*SUPUESTOS!B15)*(1+SUPUESTOS!B10)*SUPUESTOS!B12+(4*SUPUESTOS!B17+SUPUESTOS!B19+4*SUPUESTOS!B17*SUPUESTOS!B15)*SUPUESTOS!B13+SUPUESTOS!B14-((4*SUPUESTOS!B17+SUPUESTOS!B19+4*SUPUESTOS!B17*SUPUESTOS!B15)*(1+SUPUESTOS!B10)*(SUPUESTOS!B11+SUPUESTOS!B12))+SUPUESTOS!$B$40+4*SUPUESTOS!$B$42 -> 12791.66 | L55: =K55*SUPUESTOS!$B$4 -> 19187490 | M55: =4*SUPUESTOS!B18+SUPUESTOS!B20+4*SUPUESTOS!B18*SUPUESTOS!B15+(4*SUPUESTOS!B18+SUPUESTOS!B20+4*SUPUESTOS!B18*SUPUESTOS!B15)*SUPUESTOS!B10+(4*SUPUESTOS!B18+SUPUESTOS!B20+4*SUPUESTOS!B18*SUPUESTOS!B15)*(1+SUPUESTOS!B10)*SUPUESTOS!B11+(4*SUPUESTOS!B18+SUPUESTOS!B20+4*SUPUESTOS!B18*SUPUESTOS!B15)*(1+SUPUESTOS!B10)*SUPUESTOS!B12+(4*SUPUESTOS!B18+SUPUESTOS!B20+4*SUPUESTOS!B18*SUPUESTOS!B15)*SUPUESTOS!B13+SUPUESTOS!B14-((4*SUPUESTOS!B18+SUPUESTOS!B20+4*SUPUESTOS!B18*SUPUESTOS!B15)*(1+SUPUESTOS!B10)*(SUPUESTOS!B11+SUPUESTOS!B12))+SUPUESTOS!$B$40+4*SUPUESTOS!$B$42 -> 31136.85 | N55: =M55*SUPUESTOS!$B$4 -> 46705275
A56: Costo promedio por máquina — neto (USD) | K56: =K55/4 -> 3197.915 | L56: =K56*SUPUESTOS!$B$4 -> 4796872.5 | M56: =M55/4 -> 7784.2125 | N56: =M56*SUPUESTOS!$B$4 -> 11676319
A59: Columnas VIOLETA = USD × TC (SUPUESTOS!B4). Modificar TC en SUPUESTOS para actualizar automáticamente.

Sheet FLUJO_CAJA
A1: VENDINS — FLUJO DE CAJA MENSUAL (ESCENARIO BASE — 36 MESES) | USD + ARS
C2: 2 MÁQUINAS | G2: 3 MÁQUINAS | K2: 4 MÁQUINAS
A3: Período | B3: Mes | C3: CF Neto (USD) | D3: CF Acum. (USD) | E3: CF Neto (ARS ×TC) | F3: CF Acum. (ARS ×TC) | G3: CF Neto (USD) | H3: CF Acum. (USD) | I3: CF Neto (ARS ×TC) | J3: CF Acum. (ARS ×TC) | K3: CF Neto (USD) | L3: CF Acum. (USD) | M3: CF Neto (ARS ×TC) | N3: CF Acum. (ARS ×TC)
A4: Inversión Inicial | B4: 0 | C4: =-(2*SUPUESTOS!B17+SUPUESTOS!B19+2*SUPUESTOS!B17*SUPUESTOS!B15+(2*SUPUESTOS!B17+SUPUESTOS!B19+2*SUPUESTOS!B17*SUPUESTOS!B15)*SUPUESTOS!B10+(2*SUPUESTOS!B17+SUPUESTOS!B19+2*SUPUESTOS!B17*SUPUESTOS!B15)*(1+SUPUESTOS!B10)*SUPUESTOS!B11+(2*SUPUESTOS!B17+SUPUESTOS!B19+2*SUPUESTOS!B17*SUPUESTOS!B15)*(1+SUPUESTOS!B10)*SUPUESTOS!B12+(2*SUPUESTOS!B17+SUPUESTOS!B19+2*SUPUESTOS!B17*SUPUESTOS!B15)*SUPUESTOS!B13+SUPUESTOS!B14-(2*SUPUESTOS!B17+SUPUESTOS!B19+2*SUPUESTOS!B17*SUPUESTOS!B15)*(1+SUPUESTOS!B10)*(SUPUESTOS!B11+SUPUESTOS!B12)+SUPUESTOS!$B$40+2*SUPUESTOS!$B$42) -> -8007.83 | D4: =C4 -> -8007.83 | E4: =C4*SUPUESTOS!$B$4 -> -12011745 | F4: =E4 -> -12011745 | G4: =-(3*SUPUESTOS!B17+SUPUESTOS!B19+3*SUPUESTOS!B17*SUPUESTOS!B15+(3*SUPUESTOS!B17+SUPUESTOS!B19+3*SUPUESTOS!B17*SUPUESTOS!B15)*SUPUESTOS!B10+(3*SUPUESTOS!B17+SUPUESTOS!B19+3*SUPUESTOS!B17*SUPUESTOS!B15)*(1+SUPUESTOS!B10)*SUPUESTOS!B11+(3*SUPUESTOS!B17+SUPUESTOS!B19+3*SUPUESTOS!B17*SUPUESTOS!B15)*(1+SUPUESTOS!B10)*SUPUESTOS!B12+(3*SUPUESTOS!B17+SUPUESTOS!B19+3*SUPUESTOS!B17*SUPUESTOS!B15)*SUPUESTOS!B13+SUPUESTOS!B14-(3*SUPUESTOS!B17+SUPUESTOS!B19+3*SUPUESTOS!B17*SUPUESTOS!B15)*(1+SUPUESTOS!B10)*(SUPUESTOS!B11+SUPUESTOS!B12)+SUPUESTOS!$B$40+3*SUPUESTOS!$B$42) -> -10399.745 | H4: =G4 -> -10399.745 | I4: =G4*SUPUESTOS!$B$4 -> -15599618 | J4: =I4 -> -15599618 | K4: =-(4*SUPUESTOS!B17+SUPUESTOS!B19+4*SUPUESTOS!B17*SUPUESTOS!B15+(4*SUPUESTOS!B17+SUPUESTOS!B19+4*SUPUESTOS!B17*SUPUESTOS!B15)*SUPUESTOS!B10+(4*SUPUESTOS!B17+SUPUESTOS!B19+4*SUPUESTOS!B17*SUPUESTOS!B15)*(1+SUPUESTOS!B10)*SUPUESTOS!B11+(4*SUPUESTOS!B17+SUPUESTOS!B19+4*SUPUESTOS!B17*SUPUESTOS!B15)*(1+SUPUESTOS!B10)*SUPUESTOS!B12+(4*SUPUESTOS!B17+SUPUESTOS!B19+4*SUPUESTOS!B17*SUPUESTOS!B15)*SUPUESTOS!B13+SUPUESTOS!B14-(4*SUPUESTOS!B17+SUPUESTOS!B19+4*SUPUESTOS!B17*SUPUESTOS!B15)*(1+SUPUESTOS!B10)*(SUPUESTOS!B11+SUPUESTOS!B12)+SUPUESTOS!$B$40+4*SUPUESTOS!$B$42) -> -12791.66 | L4: =K4 -> -12791.66 | M4: =K4*SUPUESTOS!$B$4 -> -19187490 | N4: =M4 -> -19187490
A5: Mes 01 | B5: 1 | C5: =2*(SUPUESTOS!B23*(1-SUPUESTOS!B25-SUPUESTOS!B26-SUPUESTOS!B27)-SUPUESTOS!B28-SUPUESTOS!B29)-SUPUESTOS!B35 -> 241 | D5: =D4+C5 -> -7766.83 | E5: =C5*SUPUESTOS!$B$4 -> 361500 | F5: =F4+E5 -> -11650245 | G5: =3*(SUPUESTOS!B23*(1-SUPUESTOS!B25-SUPUESTOS!B26-SUPUESTOS!B27)-SUPUESTOS!B28-SUPUESTOS!B29)-SUPUESTOS!B35 -> 409 | H5: =H4+G5 -> -9990.745 | I5: =G5*SUPUESTOS!$B$4 -> 613500 | J5: =J4+I5 -> -14986118 | K5: =4*(SUPUESTOS!B23*(1-SUPUESTOS!B25-SUPUESTOS!B26-SUPUESTOS!B27)-SUPUESTOS!B28-SUPUESTOS!B29)-SUPUESTOS!B35 -> 577 | L5: =L4+K5 -> -12214.66 | M5: =K5*SUPUESTOS!$B$4 -> 865500 | N5: =N4+M5 -> -18321990
A6: Mes 02 | B6: 2 | C6: =2*(SUPUESTOS!B23*(1-SUPUESTOS!B25-SUPUESTOS!B26-SUPUESTOS!B27)-SUPUESTOS!B28-SUPUESTOS!B29)-SUPUESTOS!B35 -> 241 | D6: =D5+C6 -> -7525.83 | E6: =C6*SUPUESTOS!$B$4 -> 361500 | F6: =F5+E6 -> -11288745 | G6: =3*(SUPUESTOS!B23*(1-SUPUESTOS!B25-SUPUESTOS!B26-SUPUESTOS!B27)-SUPUESTOS!B28-SUPUESTOS!B29)-SUPUESTOS!B35 -> 409 | H6: =H5+G6 -> -9581.745 | I6: =G6*SUPUESTOS!$B$4 -> 613500 | J6: =J5+I6 -> -14372618 | K6: =4*(SUPUESTOS!B23*(1-SUPUESTOS!B25-SUPUESTOS!B26-SUPUESTOS!B27)-SUPUESTOS!B28-SUPUESTOS!B29)-SUPUESTOS!B35 -> 577 | L6: =L5+K6 -> -11637.66 | M6: =K6*SUPUESTOS!$B$4 -> 865500 | N6: =N5+M6 -> -17456490
A7: Mes 03 | B7: 3 | C7: =2*(SUPUESTOS!B23*(1-SUPUESTOS!B25-SUPUESTOS!B26-SUPUESTOS!B27)-SUPUESTOS!B28-SUPUESTOS!B29)-SUPUESTOS!B35 -> 241 | D7: =D6+C7 -> -7284.83 | E7: =C7*SUPUESTOS!$B$4 -> 361500 | F7: =F6+E7 -> -10927245 | G7: =3*(SUPUESTOS!B23*(1-SUPUESTOS!B25-SUPUESTOS!B26-SUPUESTOS!B27)-SUPUESTOS!B28-SUPUESTOS!B29)-SUPUESTOS!B35 -> 409 | H7: =H6+G7 -> -9172.745 | I7: =G7*SUPUESTOS!$B$4 -> 613500 | J7: =J6+I7 -> -13759118 | K7: =4*(SUPUESTOS!B23*(1-SUPUESTOS!B25-SUPUESTOS!B26-SUPUESTOS!B27)-SUPUESTOS!B28-SUPUESTOS!B29)-SUPUESTOS!B35 -> 577 | L7: =L6+K7 -> -11060.66 | M7: =K7*SUPUESTOS!$B$4 -> 865500 | N7: =N6+M7 -> -16590990
A8: Mes 04 | B8: 4 | C8: =2*(SUPUESTOS!B23*(1-SUPUESTOS!B25-SUPUESTOS!B26-SUPUESTOS!B27)-SUPUESTOS!B28-SUPUESTOS!B29)-SUPUESTOS!B35 -> 241 | D8: =D7+C8 -> -7043.83 | E8: =C8*SUPUESTOS!$B$4 -> 361500 | F8: =F7+E8 -> -10565745 | G8: =3*(SUPUESTOS!B23*(1-SUPUESTOS!B25-SUPUESTOS!B26-SUPUESTOS!B27)-SUPUESTOS!B28-SUPUESTOS!B29)-SUPUESTOS!B35 -> 409 | H8: =H7+G8 -> -8763.745 | I8: =G8*SUPUESTOS!$B$4 -> 613500 | J8: =J7+I8 -> -13145618 | K8: =4*(SUPUESTOS!B23*(1-SUPUESTOS!B25-SUPUESTOS!B26-SUPUESTOS!B27)-SUPUESTOS!B28-SUPUESTOS!B29)-SUPUESTOS!B35 -> 577 | L8: =L7+K8 -> -10483.66 | M8: =K8*SUPUESTOS!$B$4 -> 865500 | N8: =N7+M8 -> -15725490
A9: Mes 05 | B9: 5 | C9: =2*(SUPUESTOS!B23*(1-SUPUESTOS!B25-SUPUESTOS!B26-SUPUESTOS!B27)-SUPUESTOS!B28-SUPUESTOS!B29)-SUPUESTOS!B35 -> 241 | D9: =D8+C9 -> -6802.83 | E9: =C9*SUPUESTOS!$B$4 -> 361500 | F9: =F8+E9 -> -10204245 | G9: =3*(SUPUESTOS!B23*(1-SUPUESTOS!B25-SUPUESTOS!B26-SUPUESTOS!B27)-SUPUESTOS!B28-SUPUESTOS!B29)-SUPUESTOS!B35 -> 409 | H9: =H8+G9 -> -8354.745 | I9: =G9*SUPUESTOS!$B$4 -> 613500 | J9: =J8+I9 -> -12532118 | K9: =4*(SUPUESTOS!B23*(1-SUPUESTOS!B25-SUPUESTOS!B26-SUPUESTOS!B27)-SUPUESTOS!B28-SUPUESTOS!B29)-SUPUESTOS!B35 -> 577 | L9: =L8+K9 -> -9906.66 | M9: =K9*SUPUESTOS!$B$4 -> 865500 | N9: =N8+M9 -> -14859990
A10: Mes 06 | B10: 6 | C10: =2*(SUPUESTOS!B23*(1-SUPUESTOS!B25-SUPUESTOS!B26-SUPUESTOS!B27)-SUPUESTOS!B28-SUPUESTOS!B29)-SUPUESTOS!B35 -> 241 | D10: =D9+C10 -> -6561.83 | E10: =C10*SUPUESTOS!$B$4 -> 361500 | F10: =F9+E10 -> -9842745 | G10: =3*(SUPUESTOS!B23*(1-SUPUESTOS!B25-SUPUESTOS!B26-SUPUESTOS!B27)-SUPUESTOS!B28-SUPUESTOS!B29)-SUPUESTOS!B35 -> 409 | H10: =H9+G10 -> -7945.745 | I10: =G10*SUPUESTOS!$B$4 -> 613500 | J10: =J9+I10 -> -11918618 | K10: =4*(SUPUESTOS!B23*(1-SUPUESTOS!B25-SUPUESTOS!B26-SUPUESTOS!B27)-SUPUESTOS!B28-SUPUESTOS!B29)-SUPUESTOS!B35 -> 577 | L10: =L9+K10 -> -9329.66 | M10: =K10*SUPUESTOS!$B$4 -> 865500 | N10: =N9+M10 -> -13994490
A11: Mes 07 | B11: 7 | C11: =2*(SUPUESTOS!B23*(1-SUPUESTOS!B25-SUPUESTOS!B26-SUPUESTOS!B27)-SUPUESTOS!B28-SUPUESTOS!B29)-SUPUESTOS!B35 -> 241 | D11: =D10+C11 -> -6320.83 | E11: =C11*SUPUESTOS!$B$4 -> 361500 | F11: =F10+E11 -> -9481245 | G11: =3*(SUPUESTOS!B23*(1-SUPUESTOS!B25-SUPUESTOS!B26-SUPUESTOS!B27)-SUPUESTOS!B28-SUPUESTOS!B29)-SUPUESTOS!B35 -> 409 | H11: =H10+G11 -> -7536.745 | I11: =G11*SUPUESTOS!$B$4 -> 613500 | J11: =J10+I11 -> -11305118 | K11: =4*(SUPUESTOS!B23*(1-SUPUESTOS!B25-SUPUESTOS!B26-SUPUESTOS!B27)-SUPUESTOS!B28-SUPUESTOS!B29)-SUPUESTOS!B35 -> 577 | L11: =L10+K11 -> -8752.66 | M11: =K11*SUPUESTOS!$B$4 -> 865500 | N11: =N10+M11 -> -13128990
A12: Mes 08 | B12: 8 | C12: =2*(SUPUESTOS!B23*(1-SUPUESTOS!B25-SUPUESTOS!B26-SUPUESTOS!B27)-SUPUESTOS!B28-SUPUESTOS!B29)-SUPUESTOS!B35 -> 241 | D12: =D11+C12 -> -6079.83 | E12: =C12*SUPUESTOS!$B$4 -> 361500 | F12: =F11+E12 -> -9119745 | G12: =3*(SUPUESTOS!B23*(1-SUPUESTOS!B25-SUPUESTOS!B26-SUPUESTOS!B27)-SUPUESTOS!B28-SUPUESTOS!B29)-SUPUESTOS!B35 -> 409 | H12: =H11+G12 -> -7127.745 | I12: =G12*SUPUESTOS!$B$4 -> 613500 | J12: =J11+I12 -> -10691618 | K12: =4*(SUPUESTOS!B23*(1-SUPUESTOS!B25-SUPUESTOS!B26-SUPUESTOS!B27)-SUPUESTOS!B28-SUPUESTOS!B29)-SUPUESTOS!B35 -> 577 | L12: =L11+K12 -> -8175.66 | M12: =K12*SUPUESTOS!$B$4 -> 865500 | N12: =N11+M12 -> -12263490
A13: Mes 09 | B13: 9 | C13: =2*(SUPUESTOS!B23*(1-SUPUESTOS!B25-SUPUESTOS!B26-SUPUESTOS!B27)-SUPUESTOS!B28-SUPUESTOS!B29)-SUPUESTOS!B35 -> 241 | D13: =D12+C13 -> -5838.83 | E13: =C13*SUPUESTOS!$B$4 -> 361500 | F13: =F12+E13 -> -8758245 | G13: =3*(SUPUESTOS!B23*(1-SUPUESTOS!B25-SUPUESTOS!B26-SUPUESTOS!B27)-SUPUESTOS!B28-SUPUESTOS!B29)-SUPUESTOS!B35 -> 409 | H13: =H12+G13 -> -6718.745 | I13: =G13*SUPUESTOS!$B$4 -> 613500 | J13: =J12+I13 -> -10078118 | K13: =4*(SUPUESTOS!B23*(1-SUPUESTOS!B25-SUPUESTOS!B26-SUPUESTOS!B27)-SUPUESTOS!B28-SUPUESTOS!B29)-SUPUESTOS!B35 -> 577 | L13: =L12+K13 -> -7598.66 | M13: =K13*SUPUESTOS!$B$4 -> 865500 | N13: =N12+M13 -> -11397990
A14: Mes 10 | B14: 10 | C14: =2*(SUPUESTOS!B23*(1-SUPUESTOS!B25-SUPUESTOS!B26-SUPUESTOS!B27)-SUPUESTOS!B28-SUPUESTOS!B29)-SUPUESTOS!B35 -> 241 | D14: =D13+C14 -> -5597.83 | E14: =C14*SUPUESTOS!$B$4 -> 361500 | F14: =F13+E14 -> -8396745 | G14: =3*(SUPUESTOS!B23*(1-SUPUESTOS!B25-SUPUESTOS!B26-SUPUESTOS!B27)-SUPUESTOS!B28-SUPUESTOS!B29)-SUPUESTOS!B35 -> 409 | H14: =H13+G14 -> -6309.745 | I14: =G14*SUPUESTOS!$B$4 -> 613500 | J14: =J13+I14 -> -9464617.5 | K14: =4*(SUPUESTOS!B23*(1-SUPUESTOS!B25-SUPUESTOS!B26-SUPUESTOS!B27)-SUPUESTOS!B28-SUPUESTOS!B29)-SUPUESTOS!B35 -> 577 | L14: =L13+K14 -> -7021.66 | M14: =K14*SUPUESTOS!$B$4 -> 865500 | N14: =N13+M14 -> -10532490
A15: Mes 11 | B15: 11 | C15: =2*(SUPUESTOS!B23*(1-SUPUESTOS!B25-SUPUESTOS!B26-SUPUESTOS!B27)-SUPUESTOS!B28-SUPUESTOS!B29)-SUPUESTOS!B35 -> 241 | D15: =D14+C15 -> -5356.83 | E15: =C15*SUPUESTOS!$B$4 -> 361500 | F15: =F14+E15 -> -8035245 | G15: =3*(SUPUESTOS!B23*(1-SUPUESTOS!B25-SUPUESTOS!B26-SUPUESTOS!B27)-SUPUESTOS!B28-SUPUESTOS!B29)-SUPUESTOS!B35 -> 409 | H15: =H14+G15 -> -5900.745 | I15: =G15*SUPUESTOS!$B$4 -> 613500 | J15: =J14+I15 -> -8851117.5 | K15: =4*(SUPUESTOS!B23*(1-SUPUESTOS!B25-SUPUESTOS!B26-SUPUESTOS!B27)-SUPUESTOS!B28-SUPUESTOS!B29)-SUPUESTOS!B35 -> 577 | L15: =L14+K15 -> -6444.66 | M15: =K15*SUPUESTOS!$B$4 -> 865500 | N15: =N14+M15 -> -9666990
A16: Mes 12 | B16: 12 | C16: =2*(SUPUESTOS!B23*(1-SUPUESTOS!B25-SUPUESTOS!B26-SUPUESTOS!B27)-SUPUESTOS!B28-SUPUESTOS!B29)-SUPUESTOS!B35 -> 241 | D16: =D15+C16 -> -5115.83 | E16: =C16*SUPUESTOS!$B$4 -> 361500 | F16: =F15+E16 -> -7673745 | G16: =3*(SUPUESTOS!B23*(1-SUPUESTOS!B25-SUPUESTOS!B26-SUPUESTOS!B27)-SUPUESTOS!B28-SUPUESTOS!B29)-SUPUESTOS!B35 -> 409 | H16: =H15+G16 -> -5491.745 | I16: =G16*SUPUESTOS!$B$4 -> 613500 | J16: =J15+I16 -> -8237617.5 | K16: =4*(SUPUESTOS!B23*(1-SUPUESTOS!B25-SUPUESTOS!B26-SUPUESTOS!B27)-SUPUESTOS!B28-SUPUESTOS!B29)-SUPUESTOS!B35 -> 577 | L16: =L15+K16 -> -5867.66 | M16: =K16*SUPUESTOS!$B$4 -> 865500 | N16: =N15+M16 -> -8801490
A17: Mes 13 | B17: 13 | C17: =2*(SUPUESTOS!B23*(1-SUPUESTOS!B25-SUPUESTOS!B26-SUPUESTOS!B27)-SUPUESTOS!B28-SUPUESTOS!B29)-SUPUESTOS!B35 -> 241 | D17: =D16+C17 -> -4874.83 | E17: =C17*SUPUESTOS!$B$4 -> 361500 | F17: =F16+E17 -> -7312245 | G17: =3*(SUPUESTOS!B23*(1-SUPUESTOS!B25-SUPUESTOS!B26-SUPUESTOS!B27)-SUPUESTOS!B28-SUPUESTOS!B29)-SUPUESTOS!B35 -> 409 | H17: =H16+G17 -> -5082.745 | I17: =G17*SUPUESTOS!$B$4 -> 613500 | J17: =J16+I17 -> -7624117.5 | K17: =4*(SUPUESTOS!B23*(1-SUPUESTOS!B25-SUPUESTOS!B26-SUPUESTOS!B27)-SUPUESTOS!B28-SUPUESTOS!B29)-SUPUESTOS!B35 -> 577 | L17: =L16+K17 -> -5290.66 | M17: =K17*SUPUESTOS!$B$4 -> 865500 | N17: =N16+M17 -> -7935990
A18: Mes 14 | B18: 14 | C18: =2*(SUPUESTOS!B23*(1-SUPUESTOS!B25-SUPUESTOS!B26-SUPUESTOS!B27)-SUPUESTOS!B28-SUPUESTOS!B29)-SUPUESTOS!B35 -> 241 | D18: =D17+C18 -> -4633.83 | E18: =C18*SUPUESTOS!$B$4 -> 361500 | F18: =F17+E18 -> -6950745 | G18: =3*(SUPUESTOS!B23*(1-SUPUESTOS!B25-SUPUESTOS!B26-SUPUESTOS!B27)-SUPUESTOS!B28-SUPUESTOS!B29)-SUPUESTOS!B35 -> 409 | H18: =H17+G18 -> -4673.745 | I18: =G18*SUPUESTOS!$B$4 -> 613500 | J18: =J17+I18 -> -7010617.5 | K18: =4*(SUPUESTOS!B23*(1-SUPUESTOS!B25-SUPUESTOS!B26-SUPUESTOS!B27)-SUPUESTOS!B28-SUPUESTOS!B29)-SUPUESTOS!B35 -> 577 | L18: =L17+K18 -> -4713.66 | M18: =K18*SUPUESTOS!$B$4 -> 865500 | N18: =N17+M18 -> -7070490
A19: Mes 15 | B19: 15 | C19: =2*(SUPUESTOS!B23*(1-SUPUESTOS!B25-SUPUESTOS!B26-SUPUESTOS!B27)-SUPUESTOS!B28-SUPUESTOS!B29)-SUPUESTOS!B35 -> 241 | D19: =D18+C19 -> -4392.83 | E19: =C19*SUPUESTOS!$B$4 -> 361500 | F19: =F18+E19 -> -6589245 | G19: =3*(SUPUESTOS!B23*(1-SUPUESTOS!B25-SUPUESTOS!B26-SUPUESTOS!B27)-SUPUESTOS!B28-SUPUESTOS!B29)-SUPUESTOS!B35 -> 409 | H19: =H18+G19 -> -4264.745 | I19: =G19*SUPUESTOS!$B$4 -> 613500 | J19: =J18+I19 -> -6397117.5 | K19: =4*(SUPUESTOS!B23*(1-SUPUESTOS!B25-SUPUESTOS!B26-SUPUESTOS!B27)-SUPUESTOS!B28-SUPUESTOS!B29)-SUPUESTOS!B35 -> 577 | L19: =L18+K19 -> -4136.66 | M19: =K19*SUPUESTOS!$B$4 -> 865500 | N19: =N18+M19 -> -6204990
A20: Mes 16 | B20: 16 | C20: =2*(SUPUESTOS!B23*(1-SUPUESTOS!B25-SUPUESTOS!B26-SUPUESTOS!B27)-SUPUESTOS!B28-SUPUESTOS!B29)-SUPUESTOS!B35 -> 241 | D20: =D19+C20 -> -4151.83 | E20: =C20*SUPUESTOS!$B$4 -> 361500 | F20: =F19+E20 -> -6227745 | G20: =3*(SUPUESTOS!B23*(1-SUPUESTOS!B25-SUPUESTOS!B26-SUPUESTOS!B27)-SUPUESTOS!B28-SUPUESTOS!B29)-SUPUESTOS!B35 -> 409 | H20: =H19+G20 -> -3855.745 | I20: =G20*SUPUESTOS!$B$4 -> 613500 | J20: =J19+I20 -> -5783617.5 | K20: =4*(SUPUESTOS!B23*(1-SUPUESTOS!B25-SUPUESTOS!B26-SUPUESTOS!B27)-SUPUESTOS!B28-SUPUESTOS!B29)-SUPUESTOS!B35 -> 577 | L20: =L19+K20 -> -3559.66 | M20: =K20*SUPUESTOS!$B$4 -> 865500 | N20: =N19+M20 -> -5339490
A21: Mes 17 | B21: 17 | C21: =2*(SUPUESTOS!B23*(1-SUPUESTOS!B25-SUPUESTOS!B26-SUPUESTOS!B27)-SUPUESTOS!B28-SUPUESTOS!B29)-SUPUESTOS!B35 -> 241 | D21: =D20+C21 -> -3910.83 | E21: =C21*SUPUESTOS!$B$4 -> 361500 | F21: =F20+E21 -> -5866245 | G21: =3*(SUPUESTOS!B23*(1-SUPUESTOS!B25-SUPUESTOS!B26-SUPUESTOS!B27)-SUPUESTOS!B28-SUPUESTOS!B29)-SUPUESTOS!B35 -> 409 | H21: =H20+G21 -> -3446.745 | I21: =G21*SUPUESTOS!$B$4 -> 613500 | J21: =J20+I21 -> -5170117.5 | K21: =4*(SUPUESTOS!B23*(1-SUPUESTOS!B25-SUPUESTOS!B26-SUPUESTOS!B27)-SUPUESTOS!B28-SUPUESTOS!B29)-SUPUESTOS!B35 -> 577 | L21: =L20+K21 -> -2982.66 | M21: =K21*SUPUESTOS!$B$4 -> 865500 | N21: =N20+M21 -> -4473990
A22: Mes 18 | B22: 18 | C22: =2*(SUPUESTOS!B23*(1-SUPUESTOS!B25-SUPUESTOS!B26-SUPUESTOS!B27)-SUPUESTOS!B28-SUPUESTOS!B29)-SUPUESTOS!B35 -> 241 | D22: =D21+C22 -> -3669.83 | E22: =C22*SUPUESTOS!$B$4 -> 361500 | F22: =F21+E22 -> -5504745 | G22: =3*(SUPUESTOS!B23*(1-SUPUESTOS!B25-SUPUESTOS!B26-SUPUESTOS!B27)-SUPUESTOS!B28-SUPUESTOS!B29)-SUPUESTOS!B35 -> 409 | H22: =H21+G22 -> -3037.745 | I22: =G22*SUPUESTOS!$B$4 -> 613500 | J22: =J21+I22 -> -4556617.5 | K22: =4*(SUPUESTOS!B23*(1-SUPUESTOS!B25-SUPUESTOS!B26-SUPUESTOS!B27)-SUPUESTOS!B28-SUPUESTOS!B29)-SUPUESTOS!B35 -> 577 | L22: =L21+K22 -> -2405.66 | M22: =K22*SUPUESTOS!$B$4 -> 865500 | N22: =N21+M22 -> -3608490
A23: Mes 19 | B23: 19 | C23: =2*(SUPUESTOS!B23*(1-SUPUESTOS!B25-SUPUESTOS!B26-SUPUESTOS!B27)-SUPUESTOS!B28-SUPUESTOS!B29)-SUPUESTOS!B35 -> 241 | D23: =D22+C23 -> -3428.83 | E23: =C23*SUPUESTOS!$B$4 -> 361500 | F23: =F22+E23 -> -5143245 | G23: =3*(SUPUESTOS!B23*(1-SUPUESTOS!B25-SUPUESTOS!B26-SUPUESTOS!B27)-SUPUESTOS!B28-SUPUESTOS!B29)-SUPUESTOS!B35 -> 409 | H23: =H22+G23 -> -2628.745 | I23: =G23*SUPUESTOS!$B$4 -> 613500 | J23: =J22+I23 -> -3943117.5 | K23: =4*(SUPUESTOS!B23*(1-SUPUESTOS!B25-SUPUESTOS!B26-SUPUESTOS!B27)-SUPUESTOS!B28-SUPUESTOS!B29)-SUPUESTOS!B35 -> 577 | L23: =L22+K23 -> -1828.66 | M23: =K23*SUPUESTOS!$B$4 -> 865500 | N23: =N22+M23 -> -2742990
A24: Mes 20 | B24: 20 | C24: =2*(SUPUESTOS!B23*(1-SUPUESTOS!B25-SUPUESTOS!B26-SUPUESTOS!B27)-SUPUESTOS!B28-SUPUESTOS!B29)-SUPUESTOS!B35 -> 241 | D24: =D23+C24 -> -3187.83 | E24: =C24*SUPUESTOS!$B$4 -> 361500 | F24: =F23+E24 -> -4781745 | G24: =3*(SUPUESTOS!B23*(1-SUPUESTOS!B25-SUPUESTOS!B26-SUPUESTOS!B27)-SUPUESTOS!B28-SUPUESTOS!B29)-SUPUESTOS!B35 -> 409 | H24: =H23+G24 -> -2219.745 | I24: =G24*SUPUESTOS!$B$4 -> 613500 | J24: =J23+I24 -> -3329617.5 | K24: =4*(SUPUESTOS!B23*(1-SUPUESTOS!B25-SUPUESTOS!B26-SUPUESTOS!B27)-SUPUESTOS!B28-SUPUESTOS!B29)-SUPUESTOS!B35 -> 577 | L24: =L23+K24 -> -1251.66 | M24: =K24*SUPUESTOS!$B$4 -> 865500 | N24: =N23+M24 -> -1877490
A25: Mes 21 | B25: 21 | C25: =2*(SUPUESTOS!B23*(1-SUPUESTOS!B25-SUPUESTOS!B26-SUPUESTOS!B27)-SUPUESTOS!B28-SUPUESTOS!B29)-SUPUESTOS!B35 -> 241 | D25: =D24+C25 -> -2946.83 | E25: =C25*SUPUESTOS!$B$4 -> 361500 | F25: =F24+E25 -> -4420245 | G25: =3*(SUPUESTOS!B23*(1-SUPUESTOS!B25-SUPUESTOS!B26-SUPUESTOS!B27)-SUPUESTOS!B28-SUPUESTOS!B29)-SUPUESTOS!B35 -> 409 | H25: =H24+G25 -> -1810.745 | I25: =G25*SUPUESTOS!$B$4 -> 613500 | J25: =J24+I25 -> -2716117.5 | K25: =4*(SUPUESTOS!B23*(1-SUPUESTOS!B25-SUPUESTOS!B26-SUPUESTOS!B27)-SUPUESTOS!B28-SUPUESTOS!B29)-SUPUESTOS!B35 -> 577 | L25: =L24+K25 -> -674.66 | M25: =K25*SUPUESTOS!$B$4 -> 865500 | N25: =N24+M25 -> -1011990
A26: Mes 22 | B26: 22 | C26: =2*(SUPUESTOS!B23*(1-SUPUESTOS!B25-SUPUESTOS!B26-SUPUESTOS!B27)-SUPUESTOS!B28-SUPUESTOS!B29)-SUPUESTOS!B35 -> 241 | D26: =D25+C26 -> -2705.83 | E26: =C26*SUPUESTOS!$B$4 -> 361500 | F26: =F25+E26 -> -4058745 | G26: =3*(SUPUESTOS!B23*(1-SUPUESTOS!B25-SUPUESTOS!B26-SUPUESTOS!B27)-SUPUESTOS!B28-SUPUESTOS!B29)-SUPUESTOS!B35 -> 409 | H26: =H25+G26 -> -1401.745 | I26: =G26*SUPUESTOS!$B$4 -> 613500 | J26: =J25+I26 -> -2102617.5 | K26: =4*(SUPUESTOS!B23*(1-SUPUESTOS!B25-SUPUESTOS!B26-SUPUESTOS!B27)-SUPUESTOS!B28-SUPUESTOS!B29)-SUPUESTOS!B35 -> 577 | L26: =L25+K26 -> -97.66 | M26: =K26*SUPUESTOS!$B$4 -> 865500 | N26: =N25+M26 -> -146490
A27: Mes 23 | B27: 23 | C27: =2*(SUPUESTOS!B23*(1-SUPUESTOS!B25-SUPUESTOS!B26-SUPUESTOS!B27)-SUPUESTOS!B28-SUPUESTOS!B29)-SUPUESTOS!B35 -> 241 | D27: =D26+C27 -> -2464.83 | E27: =C27*SUPUESTOS!$B$4 -> 361500 | F27: =F26+E27 -> -3697245 | G27: =3*(SUPUESTOS!B23*(1-SUPUESTOS!B25-SUPUESTOS!B26-SUPUESTOS!B27)-SUPUESTOS!B28-SUPUESTOS!B29)-SUPUESTOS!B35 -> 409 | H27: =H26+G27 -> -992.745 | I27: =G27*SUPUESTOS!$B$4 -> 613500 | J27: =J26+I27 -> -1489117.5 | K27: =4*(SUPUESTOS!B23*(1-SUPUESTOS!B25-SUPUESTOS!B26-SUPUESTOS!B27)-SUPUESTOS!B28-SUPUESTOS!B29)-SUPUESTOS!B35 -> 577 | L27: =L26+K27 -> 479.34 | M27: =K27*SUPUESTOS!$B$4 -> 865500 | N27: =N26+M27 -> 719010
A28: Mes 24 | B28: 24 | C28: =2*(SUPUESTOS!B23*(1-SUPUESTOS!B25-SUPUESTOS!B26-SUPUESTOS!B27)-SUPUESTOS!B28-SUPUESTOS!B29)-SUPUESTOS!B35 -> 241 | D28: =D27+C28 -> -2223.83 | E28: =C28*SUPUESTOS!$B$4 -> 361500 | F28: =F27+E28 -> -3335745 | G28: =3*(SUPUESTOS!B23*(1-SUPUESTOS!B25-SUPUESTOS!B26-SUPUESTOS!B27)-SUPUESTOS!B28-SUPUESTOS!B29)-SUPUESTOS!B35 -> 409 | H28: =H27+G28 -> -583.745 | I28: =G28*SUPUESTOS!$B$4 -> 613500 | J28: =J27+I28 -> -875617.5 | K28: =4*(SUPUESTOS!B23*(1-SUPUESTOS!B25-SUPUESTOS!B26-SUPUESTOS!B27)-SUPUESTOS!B28-SUPUESTOS!B29)-SUPUESTOS!B35 -> 577 | L28: =L27+K28 -> 1056.34 | M28: =K28*SUPUESTOS!$B$4 -> 865500 | N28: =N27+M28 -> 1584510
A29: Mes 25 | B29: 25 | C29: =2*(SUPUESTOS!B23*(1-SUPUESTOS!B25-SUPUESTOS!B26-SUPUESTOS!B27)-SUPUESTOS!B28-SUPUESTOS!B29)-SUPUESTOS!B35 -> 241 | D29: =D28+C29 -> -1982.83 | E29: =C29*SUPUESTOS!$B$4 -> 361500 | F29: =F28+E29 -> -2974245 | G29: =3*(SUPUESTOS!B23*(1-SUPUESTOS!B25-SUPUESTOS!B26-SUPUESTOS!B27)-SUPUESTOS!B28-SUPUESTOS!B29)-SUPUESTOS!B35 -> 409 | H29: =H28+G29 -> -174.745 | I29: =G29*SUPUESTOS!$B$4 -> 613500 | J29: =J28+I29 -> -262117.5 | K29: =4*(SUPUESTOS!B23*(1-SUPUESTOS!B25-SUPUESTOS!B26-SUPUESTOS!B27)-SUPUESTOS!B28-SUPUESTOS!B29)-SUPUESTOS!B35 -> 577 | L29: =L28+K29 -> 1633.34 | M29: =K29*SUPUESTOS!$B$4 -> 865500 | N29: =N28+M29 -> 2450010
A30: Mes 26 | B30: 26 | C30: =2*(SUPUESTOS!B23*(1-SUPUESTOS!B25-SUPUESTOS!B26-SUPUESTOS!B27)-SUPUESTOS!B28-SUPUESTOS!B29)-SUPUESTOS!B35 -> 241 | D30: =D29+C30 -> -1741.83 | E30: =C30*SUPUESTOS!$B$4 -> 361500 | F30: =F29+E30 -> -2612745 | G30: =3*(SUPUESTOS!B23*(1-SUPUESTOS!B25-SUPUESTOS!B26-SUPUESTOS!B27)-SUPUESTOS!B28-SUPUESTOS!B29)-SUPUESTOS!B35 -> 409 | H30: =H29+G30 -> 234.255 | I30: =G30*SUPUESTOS!$B$4 -> 613500 | J30: =J29+I30 -> 351382.5 | K30: =4*(SUPUESTOS!B23*(1-SUPUESTOS!B25-SUPUESTOS!B26-SUPUESTOS!B27)-SUPUESTOS!B28-SUPUESTOS!B29)-SUPUESTOS!B35 -> 577 | L30: =L29+K30 -> 2210.34 | M30: =K30*SUPUESTOS!$B$4 -> 865500 | N30: =N29+M30 -> 3315510
A31: Mes 27 | B31: 27 | C31: =2*(SUPUESTOS!B23*(1-SUPUESTOS!B25-SUPUESTOS!B26-SUPUESTOS!B27)-SUPUESTOS!B28-SUPUESTOS!B29)-SUPUESTOS!B35 -> 241 | D31: =D30+C31 -> -1500.83 | E31: =C31*SUPUESTOS!$B$4 -> 361500 | F31: =F30+E31 -> -2251245 | G31: =3*(SUPUESTOS!B23*(1-SUPUESTOS!B25-SUPUESTOS!B26-SUPUESTOS!B27)-SUPUESTOS!B28-SUPUESTOS!B29)-SUPUESTOS!B35 -> 409 | H31: =H30+G31 -> 643.255 | I31: =G31*SUPUESTOS!$B$4 -> 613500 | J31: =J30+I31 -> 964882.5 | K31: =4*(SUPUESTOS!B23*(1-SUPUESTOS!B25-SUPUESTOS!B26-SUPUESTOS!B27)-SUPUESTOS!B28-SUPUESTOS!B29)-SUPUESTOS!B35 -> 577 | L31: =L30+K31 -> 2787.34 | M31: =K31*SUPUESTOS!$B$4 -> 865500 | N31: =N30+M31 -> 4181010
A32: Mes 28 | B32: 28 | C32: =2*(SUPUESTOS!B23*(1-SUPUESTOS!B25-SUPUESTOS!B26-SUPUESTOS!B27)-SUPUESTOS!B28-SUPUESTOS!B29)-SUPUESTOS!B35 -> 241 | D32: =D31+C32 -> -1259.83 | E32: =C32*SUPUESTOS!$B$4 -> 361500 | F32: =F31+E32 -> -1889745 | G32: =3*(SUPUESTOS!B23*(1-SUPUESTOS!B25-SUPUESTOS!B26-SUPUESTOS!B27)-SUPUESTOS!B28-SUPUESTOS!B29)-SUPUESTOS!B35 -> 409 | H32: =H31+G32 -> 1052.255 | I32: =G32*SUPUESTOS!$B$4 -> 613500 | J32: =J31+I32 -> 1578382.5 | K32: =4*(SUPUESTOS!B23*(1-SUPUESTOS!B25-SUPUESTOS!B26-SUPUESTOS!B27)-SUPUESTOS!B28-SUPUESTOS!B29)-SUPUESTOS!B35 -> 577 | L32: =L31+K32 -> 3364.34 | M32: =K32*SUPUESTOS!$B$4 -> 865500 | N32: =N31+M32 -> 5046510
A33: Mes 29 | B33: 29 | C33: =2*(SUPUESTOS!B23*(1-SUPUESTOS!B25-SUPUESTOS!B26-SUPUESTOS!B27)-SUPUESTOS!B28-SUPUESTOS!B29)-SUPUESTOS!B35 -> 241 | D33: =D32+C33 -> -1018.83 | E33: =C33*SUPUESTOS!$B$4 -> 361500 | F33: =F32+E33 -> -1528245 | G33: =3*(SUPUESTOS!B23*(1-SUPUESTOS!B25-SUPUESTOS!B26-SUPUESTOS!B27)-SUPUESTOS!B28-SUPUESTOS!B29)-SUPUESTOS!B35 -> 409 | H33: =H32+G33 -> 1461.255 | I33: =G33*SUPUESTOS!$B$4 -> 613500 | J33: =J32+I33 -> 2191882.5 | K33: =4*(SUPUESTOS!B23*(1-SUPUESTOS!B25-SUPUESTOS!B26-SUPUESTOS!B27)-SUPUESTOS!B28-SUPUESTOS!B29)-SUPUESTOS!B35 -> 577 | L33: =L32+K33 -> 3941.34 | M33: =K33*SUPUESTOS!$B$4 -> 865500 | N33: =N32+M33 -> 5912010
A34: Mes 30 | B34: 30 | C34: =2*(SUPUESTOS!B23*(1-SUPUESTOS!B25-SUPUESTOS!B26-SUPUESTOS!B27)-SUPUESTOS!B28-SUPUESTOS!B29)-SUPUESTOS!B35 -> 241 | D34: =D33+C34 -> -777.83 | E34: =C34*SUPUESTOS!$B$4 -> 361500 | F34: =F33+E34 -> -1166745 | G34: =3*(SUPUESTOS!B23*(1-SUPUESTOS!B25-SUPUESTOS!B26-SUPUESTOS!B27)-SUPUESTOS!B28-SUPUESTOS!B29)-SUPUESTOS!B35 -> 409 | H34: =H33+G34 -> 1870.255 | I34: =G34*SUPUESTOS!$B$4 -> 613500 | J34: =J33+I34 -> 2805382.5 | K34: =4*(SUPUESTOS!B23*(1-SUPUESTOS!B25-SUPUESTOS!B26-SUPUESTOS!B27)-SUPUESTOS!B28-SUPUESTOS!B29)-SUPUESTOS!B35 -> 577 | L34: =L33+K34 -> 4518.34 | M34: =K34*SUPUESTOS!$B$4 -> 865500 | N34: =N33+M34 -> 6777510
A35: Mes 31 | B35: 31 | C35: =2*(SUPUESTOS!B23*(1-SUPUESTOS!B25-SUPUESTOS!B26-SUPUESTOS!B27)-SUPUESTOS!B28-SUPUESTOS!B29)-SUPUESTOS!B35 -> 241 | D35: =D34+C35 -> -536.83 | E35: =C35*SUPUESTOS!$B$4 -> 361500 | F35: =F34+E35 -> -805245 | G35: =3*(SUPUESTOS!B23*(1-SUPUESTOS!B25-SUPUESTOS!B26-SUPUESTOS!B27)-SUPUESTOS!B28-SUPUESTOS!B29)-SUPUESTOS!B35 -> 409 | H35: =H34+G35 -> 2279.255 | I35: =G35*SUPUESTOS!$B$4 -> 613500 | J35: =J34+I35 -> 3418882.5 | K35: =4*(SUPUESTOS!B23*(1-SUPUESTOS!B25-SUPUESTOS!B26-SUPUESTOS!B27)-SUPUESTOS!B28-SUPUESTOS!B29)-SUPUESTOS!B35 -> 577 | L35: =L34+K35 -> 5095.34 | M35: =K35*SUPUESTOS!$B$4 -> 865500 | N35: =N34+M35 -> 7643010
A36: Mes 32 | B36: 32 | C36: =2*(SUPUESTOS!B23*(1-SUPUESTOS!B25-SUPUESTOS!B26-SUPUESTOS!B27)-SUPUESTOS!B28-SUPUESTOS!B29)-SUPUESTOS!B35 -> 241 | D36: =D35+C36 -> -295.83 | E36: =C36*SUPUESTOS!$B$4 -> 361500 | F36: =F35+E36 -> -443745 | G36: =3*(SUPUESTOS!B23*(1-SUPUESTOS!B25-SUPUESTOS!B26-SUPUESTOS!B27)-SUPUESTOS!B28-SUPUESTOS!B29)-SUPUESTOS!B35 -> 409 | H36: =H35+G36 -> 2688.255 | I36: =G36*SUPUESTOS!$B$4 -> 613500 | J36: =J35+I36 -> 4032382.5 | K36: =4*(SUPUESTOS!B23*(1-SUPUESTOS!B25-SUPUESTOS!B26-SUPUESTOS!B27)-SUPUESTOS!B28-SUPUESTOS!B29)-SUPUESTOS!B35 -> 577 | L36: =L35+K36 -> 5672.34 | M36: =K36*SUPUESTOS!$B$4 -> 865500 | N36: =N35+M36 -> 8508510
A37: Mes 33 | B37: 33 | C37: =2*(SUPUESTOS!B23*(1-SUPUESTOS!B25-SUPUESTOS!B26-SUPUESTOS!B27)-SUPUESTOS!B28-SUPUESTOS!B29)-SUPUESTOS!B35 -> 241 | D37: =D36+C37 -> -54.83 | E37: =C37*SUPUESTOS!$B$4 -> 361500 | F37: =F36+E37 -> -82245 | G37: =3*(SUPUESTOS!B23*(1-SUPUESTOS!B25-SUPUESTOS!B26-SUPUESTOS!B27)-SUPUESTOS!B28-SUPUESTOS!B29)-SUPUESTOS!B35 -> 409 | H37: =H36+G37 -> 3097.255 | I37: =G37*SUPUESTOS!$B$4 -> 613500 | J37: =J36+I37 -> 4645882.5 | K37: =4*(SUPUESTOS!B23*(1-SUPUESTOS!B25-SUPUESTOS!B26-SUPUESTOS!B27)-SUPUESTOS!B28-SUPUESTOS!B29)-SUPUESTOS!B35 -> 577 | L37: =L36+K37 -> 6249.34 | M37: =K37*SUPUESTOS!$B$4 -> 865500 | N37: =N36+M37 -> 9374010
A38: Mes 34 | B38: 34 | C38: =2*(SUPUESTOS!B23*(1-SUPUESTOS!B25-SUPUESTOS!B26-SUPUESTOS!B27)-SUPUESTOS!B28-SUPUESTOS!B29)-SUPUESTOS!B35 -> 241 | D38: =D37+C38 -> 186.17 | E38: =C38*SUPUESTOS!$B$4 -> 361500 | F38: =F37+E38 -> 279255 | G38: =3*(SUPUESTOS!B23*(1-SUPUESTOS!B25-SUPUESTOS!B26-SUPUESTOS!B27)-SUPUESTOS!B28-SUPUESTOS!B29)-SUPUESTOS!B35 -> 409 | H38: =H37+G38 -> 3506.255 | I38: =G38*SUPUESTOS!$B$4 -> 613500 | J38: =J37+I38 -> 5259382.5 | K38: =4*(SUPUESTOS!B23*(1-SUPUESTOS!B25-SUPUESTOS!B26-SUPUESTOS!B27)-SUPUESTOS!B28-SUPUESTOS!B29)-SUPUESTOS!B35 -> 577 | L38: =L37+K38 -> 6826.34 | M38: =K38*SUPUESTOS!$B$4 -> 865500 | N38: =N37+M38 -> 10239510
A39: Mes 35 | B39: 35 | C39: =2*(SUPUESTOS!B23*(1-SUPUESTOS!B25-SUPUESTOS!B26-SUPUESTOS!B27)-SUPUESTOS!B28-SUPUESTOS!B29)-SUPUESTOS!B35 -> 241 | D39: =D38+C39 -> 427.17 | E39: =C39*SUPUESTOS!$B$4 -> 361500 | F39: =F38+E39 -> 640755 | G39: =3*(SUPUESTOS!B23*(1-SUPUESTOS!B25-SUPUESTOS!B26-SUPUESTOS!B27)-SUPUESTOS!B28-SUPUESTOS!B29)-SUPUESTOS!B35 -> 409 | H39: =H38+G39 -> 3915.255 | I39: =G39*SUPUESTOS!$B$4 -> 613500 | J39: =J38+I39 -> 5872882.5 | K39: =4*(SUPUESTOS!B23*(1-SUPUESTOS!B25-SUPUESTOS!B26-SUPUESTOS!B27)-SUPUESTOS!B28-SUPUESTOS!B29)-SUPUESTOS!B35 -> 577 | L39: =L38+K39 -> 7403.34 | M39: =K39*SUPUESTOS!$B$4 -> 865500 | N39: =N38+M39 -> 11105010
A40: Mes 36 | B40: 36 | C40: =2*(SUPUESTOS!B23*(1-SUPUESTOS!B25-SUPUESTOS!B26-SUPUESTOS!B27)-SUPUESTOS!B28-SUPUESTOS!B29)-SUPUESTOS!B35 -> 241 | D40: =D39+C40 -> 668.17 | E40: =C40*SUPUESTOS!$B$4 -> 361500 | F40: =F39+E40 -> 1002255 | G40: =3*(SUPUESTOS!B23*(1-SUPUESTOS!B25-SUPUESTOS!B26-SUPUESTOS!B27)-SUPUESTOS!B28-SUPUESTOS!B29)-SUPUESTOS!B35 -> 409 | H40: =H39+G40 -> 4324.255 | I40: =G40*SUPUESTOS!$B$4 -> 613500 | J40: =J39+I40 -> 6486382.5 | K40: =4*(SUPUESTOS!B23*(1-SUPUESTOS!B25-SUPUESTOS!B26-SUPUESTOS!B27)-SUPUESTOS!B28-SUPUESTOS!B29)-SUPUESTOS!B35 -> 577 | L40: =L39+K40 -> 7980.34 | M40: =K40*SUPUESTOS!$B$4 -> 865500 | N40: =N39+M40 -> 11970510
A42: MÉTRICAS DEL FLUJO
A43: Métrica | C43: 2 Máq (USD) | E43: 2 Máq (ARS) | G43: 3 Máq (USD) | I43: 3 Máq (ARS) | K43: 4 Máq (USD) | M43: 4 Máq (ARS)
A44: TIR Mensual | C44: =IFERROR(IRR(C4:C40),"—") -> 0.0043977253 | E44: — | G44: =IFERROR(IRR(G4:G40),"—") -> 0.020150733 | I44: — | K44: =IFERROR(IRR(K4:K40),"—") -> 0.028977287 | M44: —
A45: TIR Anualizada | C45: =IFERROR((1+IFERROR(IRR(C4:C40),0))^12-1,"—") -> 0.054068041 | E45: — | G45: =IFERROR((1+IFERROR(IRR(G4:G40),0))^12-1,"—") -> 0.27049264 | I45: — | K45: =IFERROR((1+IFERROR(IRR(K4:K40),0))^12-1,"—") -> 0.40886526 | M45: —
A46: VAN (WACC 35%, USD) | C46: =IFERROR(NPV(SUPUESTOS!B7,C5:C40)+C4,"—") -> -2359.1517 | E46: =IF(ISNUMBER(C46),C46*SUPUESTOS!$B$4,"—") -> -3538727.6 | G46: =IFERROR(NPV(SUPUESTOS!B7,G5:G40)+G4,"—") -> -813.39888 | I46: =IF(ISNUMBER(G46),G46*SUPUESTOS!$B$4,"—") -> -1220098.3 | K46: =IFERROR(NPV(SUPUESTOS!B7,K5:K40)+K4,"—") -> 732.35397 | M46: =IF(ISNUMBER(K46),K46*SUPUESTOS!$B$4,"—") -> 1098531
A47: Mes de Recupero (Payback) | C47: =IFERROR(MATCH(0,IF(D4:D40>=0,1,0),1),">36") -> 34 | E47: — ver USD → | G47: =IFERROR(MATCH(0,IF(H4:H40>=0,1,0),1),">36") -> 26 | I47: — ver USD → | K47: =IFERROR(MATCH(0,IF(L4:L40>=0,1,0),1),">36") -> 23 | M47: — ver USD →
A49: Columnas VIOLETA = USD × TC (SUPUESTOS!B4). Modificar TC en SUPUESTOS → todo se actualiza. Escenario BASE USD 600/máq/mes.

Sheet INDICADORES
A1: VENDINS — INDICADORES FINANCIEROS: VAN / TIR / PAYBACK | USD + ARS
A3: MARGEN DE CONTRIBUCIÓN POR MÁQUINA — DESGLOSE MENSUAL
A4: Concepto | C4: PESIMISTA $300/mes USD | D4: PES. ARS | E4: BASE $600/mes USD | F4: BASE ARS | G4: OPTIMISTA $1,200 USD | H4: OPT. ARS
A5: (+) Ingresos brutos / máquina | C5: =SUPUESTOS!B22 -> 300 | D5: =C5*SUPUESTOS!$B$4 -> 450000 | E5: =SUPUESTOS!B23 -> 600 | F5: =E5*SUPUESTOS!$B$4 -> 900000 | G5: =SUPUESTOS!B24 -> 1200 | H5: =G5*SUPUESTOS!$B$4 -> 1800000
A6: (−) COGS (45%) | C6: =-SUPUESTOS!B22*SUPUESTOS!B25 -> -135 | D6: =C6*SUPUESTOS!$B$4 -> -202500 | E6: =-SUPUESTOS!B23*SUPUESTOS!B25 -> -270 | F6: =E6*SUPUESTOS!$B$4 -> -405000 | G6: =-SUPUESTOS!B24*SUPUESTOS!B25 -> -540 | H6: =G6*SUPUESTOS!$B$4 -> -810000
A7: (−) Canon locador (15%) | C7: =-SUPUESTOS!B22*SUPUESTOS!B26 -> -45 | D7: =C7*SUPUESTOS!$B$4 -> -67500 | E7: =-SUPUESTOS!B23*SUPUESTOS!B26 -> -90 | F7: =E7*SUPUESTOS!$B$4 -> -135000 | G7: =-SUPUESTOS!B24*SUPUESTOS!B26 -> -180 | H7: =G7*SUPUESTOS!$B$4 -> -270000
A8: (−) IB Neuquén (2%) | C8: =-SUPUESTOS!B22*SUPUESTOS!B27 -> -6 | D8: =C8*SUPUESTOS!$B$4 -> -9000 | E8: =-SUPUESTOS!B23*SUPUESTOS!B27 -> -12 | F8: =E8*SUPUESTOS!$B$4 -> -18000 | G8: =-SUPUESTOS!B24*SUPUESTOS!B27 -> -24 | H8: =G8*SUPUESTOS!$B$4 -> -36000
A9: (−) Mantenimiento | C9: =-SUPUESTOS!B28 -> -35 | D9: =C9*SUPUESTOS!$B$4 -> -52500 | E9: =-SUPUESTOS!B28 -> -35 | F9: =E9*SUPUESTOS!$B$4 -> -52500 | G9: =-SUPUESTOS!B28 -> -35 | H9: =G9*SUPUESTOS!$B$4 -> -52500
A10: (−) Logística | C10: =-SUPUESTOS!B29 -> -25 | D10: =C10*SUPUESTOS!$B$4 -> -37500 | E10: =-SUPUESTOS!B29 -> -25 | F10: =E10*SUPUESTOS!$B$4 -> -37500 | G10: =-SUPUESTOS!B29 -> -25 | H10: =G10*SUPUESTOS!$B$4 -> -37500
A11: contribución neta / máquina / mes | C11: =SUPUESTOS!B22*(1-SUPUESTOS!B25-SUPUESTOS!B26-SUPUESTOS!B27)-SUPUESTOS!B28-SUPUESTOS!B29 -> 54 | D11: =C11*SUPUESTOS!$B$4 -> 81000 | E11: =SUPUESTOS!B23*(1-SUPUESTOS!B25-SUPUESTOS!B26-SUPUESTOS!B27)-SUPUESTOS!B28-SUPUESTOS!B29 -> 168 | F11: =E11*SUPUESTOS!$B$4 -> 252000 | G11: =SUPUESTOS!B24*(1-SUPUESTOS!B25-SUPUESTOS!B26-SUPUESTOS!B27)-SUPUESTOS!B28-SUPUESTOS!B29 -> 396 | H11: =G11*SUPUESTOS!$B$4 -> 594000
A13: MATRIZ DE ESCENARIOS: VAN — TIR — en USD y ARS (China)
A14: Escenario | C14: 2 MÁQUINAS | F14: 3 MÁQUINAS | I14: 4 MÁQUINAS
C15: VAN (USD) | D15: TIR Anual | E15: VAN (ARS ×TC) | F15: VAN (USD) | G15: TIR Anual | H15: VAN (ARS ×TC) | I15: VAN (USD) | J15: TIR Anual | K15: VAN (ARS ×TC)
A16: PESIMISTA ($300/mes) | C16: =(-(2*SUPUESTOS!B17+SUPUESTOS!B19+2*SUPUESTOS!B17*SUPUESTOS!B15+(2*SUPUESTOS!B17+SUPUESTOS!B19+2*SUPUESTOS!B17*SUPUESTOS!B15)*SUPUESTOS!B10+(2*SUPUESTOS!B17+SUPUESTOS!B19+2*SUPUESTOS!B17*SUPUESTOS!B15)*(1+SUPUESTOS!B10)*SUPUESTOS!B11+(2*SUPUESTOS!B17+SUPUESTOS!B19+2*SUPUESTOS!B17*SUPUESTOS!B15)*(1+SUPUESTOS!B10)*SUPUESTOS!B12+(2*SUPUESTOS!B17+SUPUESTOS!B19+2*SUPUESTOS!B17*SUPUESTOS!B15)*SUPUESTOS!B13+SUPUESTOS!B14-(2*SUPUESTOS!B17+SUPUESTOS!B19+2*SUPUESTOS!B17*SUPUESTOS!B15)*(1+SUPUESTOS!B10)*(SUPUESTOS!B11+SUPUESTOS!B12)+SUPUESTOS!$B$40+2*SUPUESTOS!$B$42))+(2*(SUPUESTOS!B22*(1-SUPUESTOS!B25-SUPUESTOS!B26-SUPUESTOS!B27)-SUPUESTOS!B28-SUPUESTOS!B29)-SUPUESTOS!B35)*((1-(1+SUPUESTOS!B7)^(-36))/SUPUESTOS!B7) -> -7703.1295 | D16: =IFERROR((1+(2*(SUPUESTOS!B22*(1-SUPUESTOS!B25-SUPUESTOS!B26-SUPUESTOS!B27)-SUPUESTOS!B28-SUPUESTOS!B29)-SUPUESTOS!B35/(2*SUPUESTOS!B17+SUPUESTOS!B19+2*SUPUESTOS!B17*SUPUESTOS!B15+(2*SUPUESTOS!B17+SUPUESTOS!B19+2*SUPUESTOS!B17*SUPUESTOS!B15)*SUPUESTOS!B10+(2*SUPUESTOS!B17+SUPUESTOS!B19+2*SUPUESTOS!B17*SUPUESTOS!B15)*(1+SUPUESTOS!B10)*SUPUESTOS!B11+(2*SUPUESTOS!B17+SUPUESTOS!B19+2*SUPUESTOS!B17*SUPUESTOS!B15)*(1+SUPUESTOS!B10)*SUPUESTOS!B12+(2*SUPUESTOS!B17+SUPUESTOS!B19+2*SUPUESTOS!B17*SUPUESTOS!B15)*SUPUESTOS!B13+SUPUESTOS!B14-(2*SUPUESTOS!B17+SUPUESTOS!B19+2*SUPUESTOS!B17*SUPUESTOS!B15)*(1+SUPUESTOS!B10)*(SUPUESTOS!B11+SUPUESTOS!B12)+SUPUESTOS!$B$40+2*SUPUESTOS!$B$42)))^12-1,"—") -> 2.8089935e+24 | E16: =IF(ISNUMBER(C16),C16*SUPUESTOS!$B$4,"—") -> -11554694 | F16: =(-(3*SUPUESTOS!B17+SUPUESTOS!B19+3*SUPUESTOS!B17*SUPUESTOS!B15+(3*SUPUESTOS!B17+SUPUESTOS!B19+3*SUPUESTOS!B17*SUPUESTOS!B15)*SUPUESTOS!B10+(3*SUPUESTOS!B17+SUPUESTOS!B19+3*SUPUESTOS!B17*SUPUESTOS!B15)*(1+SUPUESTOS!B10)*SUPUESTOS!B11+(3*SUPUESTOS!B17+SUPUESTOS!B19+3*SUPUESTOS!B17*SUPUESTOS!B15)*(1+SUPUESTOS!B10)*SUPUESTOS!B12+(3*SUPUESTOS!B17+SUPUESTOS!B19+3*SUPUESTOS!B17*SUPUESTOS!B15)*SUPUESTOS!B13+SUPUESTOS!B14-(3*SUPUESTOS!B17+SUPUESTOS!B19+3*SUPUESTOS!B17*SUPUESTOS!B15)*(1+SUPUESTOS!B10)*(SUPUESTOS!B11+SUPUESTOS!B12)+SUPUESTOS!$B$40+3*SUPUESTOS!$B$42))+(3*(SUPUESTOS!B22*(1-SUPUESTOS!B25-SUPUESTOS!B26-SUPUESTOS!B27)-SUPUESTOS!B28-SUPUESTOS!B29)-SUPUESTOS!B35)*((1-(1+SUPUESTOS!B7)^(-36))/SUPUESTOS!B7) -> -8829.3656 | G16: =IFERROR((1+(3*(SUPUESTOS!B22*(1-SUPUESTOS!B25-SUPUESTOS!B26-SUPUESTOS!B27)-SUPUESTOS!B28-SUPUESTOS!B29)-SUPUESTOS!B35/(3*SUPUESTOS!B17+SUPUESTOS!B19+3*SUPUESTOS!B17*SUPUESTOS!B15+(3*SUPUESTOS!B17+SUPUESTOS!B19+3*SUPUESTOS!B17*SUPUESTOS!B15)*SUPUESTOS!B10+(3*SUPUESTOS!B17+SUPUESTOS!B19+3*SUPUESTOS!B17*SUPUESTOS!B15)*(1+SUPUESTOS!B10)*SUPUESTOS!B11+(3*SUPUESTOS!B17+SUPUESTOS!B19+3*SUPUESTOS!B17*SUPUESTOS!B15)*(1+SUPUESTOS!B10)*SUPUESTOS!B12+(3*SUPUESTOS!B17+SUPUESTOS!B19+3*SUPUESTOS!B17*SUPUESTOS!B15)*SUPUESTOS!B13+SUPUESTOS!B14-(3*SUPUESTOS!B17+SUPUESTOS!B19+3*SUPUESTOS!B17*SUPUESTOS!B15)*(1+SUPUESTOS!B10)*(SUPUESTOS!B11+SUPUESTOS!B12)+SUPUESTOS!$B$40+3*SUPUESTOS!$B$42)))^12-1,"—") -> 3.515274e+26 | H16: =IF(ISNUMBER(F16),F16*SUPUESTOS!$B$4,"—") -> -13244048 | I16: =(-(4*SUPUESTOS!B17+SUPUESTOS!B19+4*SUPUESTOS!B17*SUPUESTOS!B15+(4*SUPUESTOS!B17+SUPUESTOS!B19+4*SUPUESTOS!B17*SUPUESTOS!B15)*SUPUESTOS!B10+(4*SUPUESTOS!B17+SUPUESTOS!B19+4*SUPUESTOS!B17*SUPUESTOS!B15)*(1+SUPUESTOS!B10)*SUPUESTOS!B11+(4*SUPUESTOS!B17+SUPUESTOS!B19+4*SUPUESTOS!B17*SUPUESTOS!B15)*(1+SUPUESTOS!B10)*SUPUESTOS!B12+(4*SUPUESTOS!B17+SUPUESTOS!B19+4*SUPUESTOS!B17*SUPUESTOS!B15)*SUPUESTOS!B13+SUPUESTOS!B14-(4*SUPUESTOS!B17+SUPUESTOS!B19+4*SUPUESTOS!B17*SUPUESTOS!B15)*(1+SUPUESTOS!B10)*(SUPUESTOS!B11+SUPUESTOS!B12)+SUPUESTOS!$B$40+4*SUPUESTOS!$B$42))+(4*(SUPUESTOS!B22*(1-SUPUESTOS!B25-SUPUESTOS!B26-SUPUESTOS!B27)-SUPUESTOS!B28-SUPUESTOS!B29)-SUPUESTOS!B35)*((1-(1+SUPUESTOS!B7)^(-36))/SUPUESTOS!B7) -> -9955.6016 | J16: =IFERROR((1+(4*(SUPUESTOS!B22*(1-SUPUESTOS!B25-SUPUESTOS!B26-SUPUESTOS!B27)-SUPUESTOS!B28-SUPUESTOS!B29)-SUPUESTOS!B35/(4*SUPUESTOS!B17+SUPUESTOS!B19+4*SUPUESTOS!B17*SUPUESTOS!B15+(4*SUPUESTOS!B17+SUPUESTOS!B19+4*SUPUESTOS!B17*SUPUESTOS!B15)*SUPUESTOS!B10+(4*SUPUESTOS!B17+SUPUESTOS!B19+4*SUPUESTOS!B17*SUPUESTOS!B15)*(1+SUPUESTOS!B10)*SUPUESTOS!B11+(4*SUPUESTOS!B17+SUPUESTOS!B19+4*SUPUESTOS!B17*SUPUESTOS!B15)*(1+SUPUESTOS!B10)*SUPUESTOS!B12+(4*SUPUESTOS!B17+SUPUESTOS!B19+4*SUPUESTOS!B17*SUPUESTOS!B15)*SUPUESTOS!B13+SUPUESTOS!B14-(4*SUPUESTOS!B17+SUPUESTOS!B19+4*SUPUESTOS!B17*SUPUESTOS!B15)*(1+SUPUESTOS!B10)*(SUPUESTOS!B11+SUPUESTOS!B12)+SUPUESTOS!$B$40+4*SUPUESTOS!$B$42)))^12-1,"—") -> 1.089779e+28 | K16: =IF(ISNUMBER(I16),I16*SUPUESTOS!$B$4,"—") -> -14933402
A17: BASE ($600/mes) | C17: =(-(2*SUPUESTOS!B17+SUPUESTOS!B19+2*SUPUESTOS!B17*SUPUESTOS!B15+(2*SUPUESTOS!B17+SUPUESTOS!B19+2*SUPUESTOS!B17*SUPUESTOS!B15)*SUPUESTOS!B10+(2*SUPUESTOS!B17+SUPUESTOS!B19+2*SUPUESTOS!B17*SUPUESTOS!B15)*(1+SUPUESTOS!B10)*SUPUESTOS!B11+(2*SUPUESTOS!B17+SUPUESTOS!B19+2*SUPUESTOS!B17*SUPUESTOS!B15)*(1+SUPUESTOS!B10)*SUPUESTOS!B12+(2*SUPUESTOS!B17+SUPUESTOS!B19+2*SUPUESTOS!B17*SUPUESTOS!B15)*SUPUESTOS!B13+SUPUESTOS!B14-(2*SUPUESTOS!B17+SUPUESTOS!B19+2*SUPUESTOS!B17*SUPUESTOS!B15)*(1+SUPUESTOS!B10)*(SUPUESTOS!B11+SUPUESTOS!B12)+SUPUESTOS!$B$40+2*SUPUESTOS!$B$42))+(2*(SUPUESTOS!B23*(1-SUPUESTOS!B25-SUPUESTOS!B26-SUPUESTOS!B27)-SUPUESTOS!B28-SUPUESTOS!B29)-SUPUESTOS!B35)*((1-(1+SUPUESTOS!B7)^(-36))/SUPUESTOS!B7) -> -2359.1517 | D17: =IFERROR((1+(2*(SUPUESTOS!B23*(1-SUPUESTOS!B25-SUPUESTOS!B26-SUPUESTOS!B27)-SUPUESTOS!B28-SUPUESTOS!B29)-SUPUESTOS!B35/(2*SUPUESTOS!B17+SUPUESTOS!B19+2*SUPUESTOS!B17*SUPUESTOS!B15+(2*SUPUESTOS!B17+SUPUESTOS!B19+2*SUPUESTOS!B17*SUPUESTOS!B15)*SUPUESTOS!B10+(2*SUPUESTOS!B17+SUPUESTOS!B19+2*SUPUESTOS!B17*SUPUESTOS!B15)*(1+SUPUESTOS!B10)*SUPUESTOS!B11+(2*SUPUESTOS!B17+SUPUESTOS!B19+2*SUPUESTOS!B17*SUPUESTOS!B15)*(1+SUPUESTOS!B10)*SUPUESTOS!B12+(2*SUPUESTOS!B17+SUPUESTOS!B19+2*SUPUESTOS!B17*SUPUESTOS!B15)*SUPUESTOS!B13+SUPUESTOS!B14-(2*SUPUESTOS!B17+SUPUESTOS!B19+2*SUPUESTOS!B17*SUPUESTOS!B15)*(1+SUPUESTOS!B10)*(SUPUESTOS!B11+SUPUESTOS!B12)+SUPUESTOS!$B$40+2*SUPUESTOS!$B$42)))^12-1,"—") -> 2.1447434e+30 | E17: =IF(ISNUMBER(C17),C17*SUPUESTOS!$B$4,"—") -> -3538727.6 | F17: =(-(3*SUPUESTOS!B17+SUPUESTOS!B19+3*SUPUESTOS!B17*SUPUESTOS!B15+(3*SUPUESTOS!B17+SUPUESTOS!B19+3*SUPUESTOS!B17*SUPUESTOS!B15)*SUPUESTOS!B10+(3*SUPUESTOS!B17+SUPUESTOS!B19+3*SUPUESTOS!B17*SUPUESTOS!B15)*(1+SUPUESTOS!B10)*SUPUESTOS!B11+(3*SUPUESTOS!B17+SUPUESTOS!B19+3*SUPUESTOS!B17*SUPUESTOS!B15)*(1+SUPUESTOS!B10)*SUPUESTOS!B12+(3*SUPUESTOS!B17+SUPUESTOS!B19+3*SUPUESTOS!B17*SUPUESTOS!B15)*SUPUESTOS!B13+SUPUESTOS!B14-(3*SUPUESTOS!B17+SUPUESTOS!B19+3*SUPUESTOS!B17*SUPUESTOS!B15)*(1+SUPUESTOS!B10)*(SUPUESTOS!B11+SUPUESTOS!B12)+SUPUESTOS!$B$40+3*SUPUESTOS!$B$42))+(3*(SUPUESTOS!B23*(1-SUPUESTOS!B25-SUPUESTOS!B26-SUPUESTOS!B27)-SUPUESTOS!B28-SUPUESTOS!B29)-SUPUESTOS!B35)*((1-(1+SUPUESTOS!B7)^(-36))/SUPUESTOS!B7) -> -813.39888 | G17: =IFERROR((1+(3*(SUPUESTOS!B23*(1-SUPUESTOS!B25-SUPUESTOS!B26-SUPUESTOS!B27)-SUPUESTOS!B28-SUPUESTOS!B29)-SUPUESTOS!B35/(3*SUPUESTOS!B17+SUPUESTOS!B19+3*SUPUESTOS!B17*SUPUESTOS!B15+(3*SUPUESTOS!B17+SUPUESTOS!B19+3*SUPUESTOS!B17*SUPUESTOS!B15)*SUPUESTOS!B10+(3*SUPUESTOS!B17+SUPUESTOS!B19+3*SUPUESTOS!B17*SUPUESTOS!B15)*(1+SUPUESTOS!B10)*SUPUESTOS!B11+(3*SUPUESTOS!B17+SUPUESTOS!B19+3*SUPUESTOS!B17*SUPUESTOS!B15)*(1+SUPUESTOS!B10)*SUPUESTOS!B12+(3*SUPUESTOS!B17+SUPUESTOS!B19+3*SUPUESTOS!B17*SUPUESTOS!B15)*SUPUESTOS!B13+SUPUESTOS!B14-(3*SUPUESTOS!B17+SUPUESTOS!B19+3*SUPUESTOS!B17*SUPUESTOS!B15)*(1+SUPUESTOS!B10)*(SUPUESTOS!B11+SUPUESTOS!B12)+SUPUESTOS!$B$40+3*SUPUESTOS!$B$42)))^12-1,"—") -> 2.7504406e+32 | H17: =IF(ISNUMBER(F17),F17*SUPUESTOS!$B$4,"—") -> -1220098.3 | I17: =(-(4*SUPUESTOS!B17+SUPUESTOS!B19+4*SUPUESTOS!B17*SUPUESTOS!B15+(4*SUPUESTOS!B17+SUPUESTOS!B19+4*SUPUESTOS!B17*SUPUESTOS!B15)*SUPUESTOS!B10+(4*SUPUESTOS!B17+SUPUESTOS!B19+4*SUPUESTOS!B17*SUPUESTOS!B15)*(1+SUPUESTOS!B10)*SUPUESTOS!B11+(4*SUPUESTOS!B17+SUPUESTOS!B19+4*SUPUESTOS!B17*SUPUESTOS!B15)*(1+SUPUESTOS!B10)*SUPUESTOS!B12+(4*SUPUESTOS!B17+SUPUESTOS!B19+4*SUPUESTOS!B17*SUPUESTOS!B15)*SUPUESTOS!B13+SUPUESTOS!B14-(4*SUPUESTOS!B17+SUPUESTOS!B19+4*SUPUESTOS!B17*SUPUESTOS!B15)*(1+SUPUESTOS!B10)*(SUPUESTOS!B11+SUPUESTOS!B12)+SUPUESTOS!$B$40+4*SUPUESTOS!$B$42))+(4*(SUPUESTOS!B23*(1-SUPUESTOS!B25-SUPUESTOS!B26-SUPUESTOS!B27)-SUPUESTOS!B28-SUPUESTOS!B29)-SUPUESTOS!B35)*((1-(1+SUPUESTOS!B7)^(-36))/SUPUESTOS!B7) -> 732.35397 | J17: =IFERROR((1+(4*(SUPUESTOS!B23*(1-SUPUESTOS!B25-SUPUESTOS!B26-SUPUESTOS!B27)-SUPUESTOS!B28-SUPUESTOS!B29)-SUPUESTOS!B35/(4*SUPUESTOS!B17+SUPUESTOS!B19+4*SUPUESTOS!B17*SUPUESTOS!B15+(4*SUPUESTOS!B17+SUPUESTOS!B19+4*SUPUESTOS!B17*SUPUESTOS!B15)*SUPUESTOS!B10+(4*SUPUESTOS!B17+SUPUESTOS!B19+4*SUPUESTOS!B17*SUPUESTOS!B15)*(1+SUPUESTOS!B10)*SUPUESTOS!B11+(4*SUPUESTOS!B17+SUPUESTOS!B19+4*SUPUESTOS!B17*SUPUESTOS!B15)*(1+SUPUESTOS!B10)*SUPUESTOS!B12+(4*SUPUESTOS!B17+SUPUESTOS!B19+4*SUPUESTOS!B17*SUPUESTOS!B15)*SUPUESTOS!B13+SUPUESTOS!B14-(4*SUPUESTOS!B17+SUPUESTOS!B19+4*SUPUESTOS!B17*SUPUESTOS!B15)*(1+SUPUESTOS!B10)*(SUPUESTOS!B11+SUPUESTOS!B12)+SUPUESTOS!$B$40+4*SUPUESTOS!$B$42)))^12-1,"—") -> 8.6322351e+33 | K17: =IF(ISNUMBER(I17),I17*SUPUESTOS!$B$4,"—") -> 1098531
A18: OPTIMISTA ($1,200/mes) | C18: =(-(2*SUPUESTOS!B17+SUPUESTOS!B19+2*SUPUESTOS!B17*SUPUESTOS!B15+(2*SUPUESTOS!B17+SUPUESTOS!B19+2*SUPUESTOS!B17*SUPUESTOS!B15)*SUPUESTOS!B10+(2*SUPUESTOS!B17+SUPUESTOS!B19+2*SUPUESTOS!B17*SUPUESTOS!B15)*(1+SUPUESTOS!B10)*SUPUESTOS!B11+(2*SUPUESTOS!B17+SUPUESTOS!B19+2*SUPUESTOS!B17*SUPUESTOS!B15)*(1+SUPUESTOS!B10)*SUPUESTOS!B12+(2*SUPUESTOS!B17+SUPUESTOS!B19+2*SUPUESTOS!B17*SUPUESTOS!B15)*SUPUESTOS!B13+SUPUESTOS!B14-(2*SUPUESTOS!B17+SUPUESTOS!B19+2*SUPUESTOS!B17*SUPUESTOS!B15)*(1+SUPUESTOS!B10)*(SUPUESTOS!B11+SUPUESTOS!B12)+SUPUESTOS!$B$40+2*SUPUESTOS!$B$42))+(2*(SUPUESTOS!B24*(1-SUPUESTOS!B25-SUPUESTOS!B26-SUPUESTOS!B27)-SUPUESTOS!B28-SUPUESTOS!B29)-SUPUESTOS!B35)*((1-(1+SUPUESTOS!B7)^(-36))/SUPUESTOS!B7) -> 8328.8039 | D18: =IFERROR((1+(2*(SUPUESTOS!B24*(1-SUPUESTOS!B25-SUPUESTOS!B26-SUPUESTOS!B27)-SUPUESTOS!B28-SUPUESTOS!B29)-SUPUESTOS!B35/(2*SUPUESTOS!B17+SUPUESTOS!B19+2*SUPUESTOS!B17*SUPUESTOS!B15+(2*SUPUESTOS!B17+SUPUESTOS!B19+2*SUPUESTOS!B17*SUPUESTOS!B15)*SUPUESTOS!B10+(2*SUPUESTOS!B17+SUPUESTOS!B19+2*SUPUESTOS!B17*SUPUESTOS!B15)*(1+SUPUESTOS!B10)*SUPUESTOS!B11+(2*SUPUESTOS!B17+SUPUESTOS!B19+2*SUPUESTOS!B17*SUPUESTOS!B15)*(1+SUPUESTOS!B10)*SUPUESTOS!B12+(2*SUPUESTOS!B17+SUPUESTOS!B19+2*SUPUESTOS!B17*SUPUESTOS!B15)*SUPUESTOS!B13+SUPUESTOS!B14-(2*SUPUESTOS!B17+SUPUESTOS!B19+2*SUPUESTOS!B17*SUPUESTOS!B15)*(1+SUPUESTOS!B10)*(SUPUESTOS!B11+SUPUESTOS!B12)+SUPUESTOS!$B$40+2*SUPUESTOS!$B$42)))^12-1,"—") -> 6.1830147e+34 | E18: =IF(ISNUMBER(C18),C18*SUPUESTOS!$B$4,"—") -> 12493206 | F18: =(-(3*SUPUESTOS!B17+SUPUESTOS!B19+3*SUPUESTOS!B17*SUPUESTOS!B15+(3*SUPUESTOS!B17+SUPUESTOS!B19+3*SUPUESTOS!B17*SUPUESTOS!B15)*SUPUESTOS!B10+(3*SUPUESTOS!B17+SUPUESTOS!B19+3*SUPUESTOS!B17*SUPUESTOS!B15)*(1+SUPUESTOS!B10)*SUPUESTOS!B11+(3*SUPUESTOS!B17+SUPUESTOS!B19+3*SUPUESTOS!B17*SUPUESTOS!B15)*(1+SUPUESTOS!B10)*SUPUESTOS!B12+(3*SUPUESTOS!B17+SUPUESTOS!B19+3*SUPUESTOS!B17*SUPUESTOS!B15)*SUPUESTOS!B13+SUPUESTOS!B14-(3*SUPUESTOS!B17+SUPUESTOS!B19+3*SUPUESTOS!B17*SUPUESTOS!B15)*(1+SUPUESTOS!B10)*(SUPUESTOS!B11+SUPUESTOS!B12)+SUPUESTOS!$B$40+3*SUPUESTOS!$B$42))+(3*(SUPUESTOS!B24*(1-SUPUESTOS!B25-SUPUESTOS!B26-SUPUESTOS!B27)-SUPUESTOS!B28-SUPUESTOS!B29)-SUPUESTOS!B35)*((1-(1+SUPUESTOS!B7)^(-36))/SUPUESTOS!B7) -> 15218.534 | G18: =IFERROR((1+(3*(SUPUESTOS!B24*(1-SUPUESTOS!B25-SUPUESTOS!B26-SUPUESTOS!B27)-SUPUESTOS!B28-SUPUESTOS!B29)-SUPUESTOS!B35/(3*SUPUESTOS!B17+SUPUESTOS!B19+3*SUPUESTOS!B17*SUPUESTOS!B15+(3*SUPUESTOS!B17+SUPUESTOS!B19+3*SUPUESTOS!B17*SUPUESTOS!B15)*SUPUESTOS!B10+(3*SUPUESTOS!B17+SUPUESTOS!B19+3*SUPUESTOS!B17*SUPUESTOS!B15)*(1+SUPUESTOS!B10)*SUPUESTOS!B11+(3*SUPUESTOS!B17+SUPUESTOS!B19+3*SUPUESTOS!B17*SUPUESTOS!B15)*(1+SUPUESTOS!B10)*SUPUESTOS!B12+(3*SUPUESTOS!B17+SUPUESTOS!B19+3*SUPUESTOS!B17*SUPUESTOS!B15)*SUPUESTOS!B13+SUPUESTOS!B14-(3*SUPUESTOS!B17+SUPUESTOS!B19+3*SUPUESTOS!B17*SUPUESTOS!B15)*(1+SUPUESTOS!B10)*(SUPUESTOS!B11+SUPUESTOS!B12)+SUPUESTOS!$B$40+3*SUPUESTOS!$B$42)))^12-1,"—") -> 7.9825605e+36 | H18: =IF(ISNUMBER(F18),F18*SUPUESTOS!$B$4,"—") -> 22827802 | I18: =(-(4*SUPUESTOS!B17+SUPUESTOS!B19+4*SUPUESTOS!B17*SUPUESTOS!B15+(4*SUPUESTOS!B17+SUPUESTOS!B19+4*SUPUESTOS!B17*SUPUESTOS!B15)*SUPUESTOS!B10+(4*SUPUESTOS!B17+SUPUESTOS!B19+4*SUPUESTOS!B17*SUPUESTOS!B15)*(1+SUPUESTOS!B10)*SUPUESTOS!B11+(4*SUPUESTOS!B17+SUPUESTOS!B19+4*SUPUESTOS!B17*SUPUESTOS!B15)*(1+SUPUESTOS!B10)*SUPUESTOS!B12+(4*SUPUESTOS!B17+SUPUESTOS!B19+4*SUPUESTOS!B17*SUPUESTOS!B15)*SUPUESTOS!B13+SUPUESTOS!B14-(4*SUPUESTOS!B17+SUPUESTOS!B19+4*SUPUESTOS!B17*SUPUESTOS!B15)*(1+SUPUESTOS!B10)*(SUPUESTOS!B11+SUPUESTOS!B12)+SUPUESTOS!$B$40+4*SUPUESTOS!$B$42))+(4*(SUPUESTOS!B24*(1-SUPUESTOS!B25-SUPUESTOS!B26-SUPUESTOS!B27)-SUPUESTOS!B28-SUPUESTOS!B29)-SUPUESTOS!B35)*((1-(1+SUPUESTOS!B7)^(-36))/SUPUESTOS!B7) -> 22108.265 | J18: =IFERROR((1+(4*(SUPUESTOS!B24*(1-SUPUESTOS!B25-SUPUESTOS!B26-SUPUESTOS!B27)-SUPUESTOS!B28-SUPUESTOS!B29)-SUPUESTOS!B35/(4*SUPUESTOS!B17+SUPUESTOS!B19+4*SUPUESTOS!B17*SUPUESTOS!B15+(4*SUPUESTOS!B17+SUPUESTOS!B19+4*SUPUESTOS!B17*SUPUESTOS!B15)*SUPUESTOS!B10+(4*SUPUESTOS!B17+SUPUESTOS!B19+4*SUPUESTOS!B17*SUPUESTOS!B15)*(1+SUPUESTOS!B10)*SUPUESTOS!B11+(4*SUPUESTOS!B17+SUPUESTOS!B19+4*SUPUESTOS!B17*SUPUESTOS!B15)*(1+SUPUESTOS!B10)*SUPUESTOS!B12+(4*SUPUESTOS!B17+SUPUESTOS!B19+4*SUPUESTOS!B17*SUPUESTOS!B15)*SUPUESTOS!B13+SUPUESTOS!B14-(4*SUPUESTOS!B17+SUPUESTOS!B19+4*SUPUESTOS!B17*SUPUESTOS!B15)*(1+SUPUESTOS!B10)*(SUPUESTOS!B11+SUPUESTOS!B12)+SUPUESTOS!$B$40+4*SUPUESTOS!$B$42)))^12-1,"—") -> 2.5137772e+38 | K18: =IF(ISNUMBER(I18),I18*SUPUESTOS!$B$4,"—") -> 33162398
A20: VAN columnas VIOLETA = VAN_USD × TC (SUPUESTOS!B4). TIR es adimensional (igual en USD y ARS). Modificar TC en SUPUESTOS para actualizar.

Sheet BREAK_EVEN
A1: VENDINS — PUNTO DE EQUILIBRIO | USD + ARS
A3: PUNTO DE EQUILIBRIO POR NÚMERO DE MÁQUINAS
A4: Concepto | C4: Fórmula | E4: USD | G4: ARS (×TC)
A5: Costos Fijos Mensuales Totales | C5: =SUPUESTOS!B35 -> 95 | E5: =SUPUESTOS!B35 -> 95 | G5: =IF(ISNUMBER(E5),E5*SUPUESTOS!$B$4,"—") -> 142500
A6: Contribución / máquina — BASE (USD/mes) | C6: Rev*(1-COGS-Canon-IB)-Mant-Log | E6: =SUPUESTOS!B23*(1-SUPUESTOS!B25-SUPUESTOS!B26-SUPUESTOS!B27)-SUPUESTOS!B28-SUPUESTOS!B29 -> 168 | G6: =IF(ISNUMBER(E6),E6*SUPUESTOS!$B$4,"—") -> 252000
A7: N° mínimo de máquinas (break-even) | C7: CF_Fijos / Contribución | E7: =IFERROR(SUPUESTOS!B35/(SUPUESTOS!B23*(1-SUPUESTOS!B25-SUPUESTOS!B26-SUPUESTOS!B27)-SUPUESTOS!B28-SUPUESTOS!B29),"—") -> 0.56547619 | G7: =IF(ISNUMBER(E7),E7,"—") -> 0.56547619
A8: Ingresos totales mínimos / mes | C8: N_eq × Ingresos / máquina | E8: =IFERROR((SUPUESTOS!B35/(SUPUESTOS!B23*(1-SUPUESTOS!B25-SUPUESTOS!B26-SUPUESTOS!B27)-SUPUESTOS!B28-SUPUESTOS!B29))*SUPUESTOS!B23,"—") -> 339.28571 | G8: =IF(ISNUMBER(E8),E8*SUPUESTOS!$B$4,"—") -> 508928.57
A10: INGRESOS MÍNIMOS POR MÁQUINA (según N° de máquinas)
A11: N° Máquinas | C11: CF neto / mes (USD) | E11: Rev. mín. / máq (USD) | G11: Rev. mín. / máq (ARS ×TC) | I11: ¿Base suficiente?
A12: 1 máquina | C12: =1*(SUPUESTOS!B23*(1-SUPUESTOS!B25-SUPUESTOS!B26-SUPUESTOS!B27)-SUPUESTOS!B28-SUPUESTOS!B29)-SUPUESTOS!B35 -> 73 | E12: =(SUPUESTOS!B35/1+(SUPUESTOS!B28+SUPUESTOS!B29))/(1-SUPUESTOS!B25-SUPUESTOS!B26-SUPUESTOS!B27) -> 407.89474 | G12: =E12*SUPUESTOS!$B$4 -> 611842.11 | I12: =IF(1*(SUPUESTOS!B23*(1-SUPUESTOS!B25-SUPUESTOS!B26-SUPUESTOS!B27)-SUPUESTOS!B28-SUPUESTOS!B29)-SUPUESTOS!B35>=0,"✓ SÍ","✗ NO") -> ✓ SÍ
A13: 2 máquinas | C13: =2*(SUPUESTOS!B23*(1-SUPUESTOS!B25-SUPUESTOS!B26-SUPUESTOS!B27)-SUPUESTOS!B28-SUPUESTOS!B29)-SUPUESTOS!B35 -> 241 | E13: =(SUPUESTOS!B35/2+(SUPUESTOS!B28+SUPUESTOS!B29))/(1-SUPUESTOS!B25-SUPUESTOS!B26-SUPUESTOS!B27) -> 282.89474 | G13: =E13*SUPUESTOS!$B$4 -> 424342.11 | I13: =IF(2*(SUPUESTOS!B23*(1-SUPUESTOS!B25-SUPUESTOS!B26-SUPUESTOS!B27)-SUPUESTOS!B28-SUPUESTOS!B29)-SUPUESTOS!B35>=0,"✓ SÍ","✗ NO") -> ✓ SÍ
A14: 3 máquinas | C14: =3*(SUPUESTOS!B23*(1-SUPUESTOS!B25-SUPUESTOS!B26-SUPUESTOS!B27)-SUPUESTOS!B28-SUPUESTOS!B29)-SUPUESTOS!B35 -> 409 | E14: =(SUPUESTOS!B35/3+(SUPUESTOS!B28+SUPUESTOS!B29))/(1-SUPUESTOS!B25-SUPUESTOS!B26-SUPUESTOS!B27) -> 241.22807 | G14: =E14*SUPUESTOS!$B$4 -> 361842.11 | I14: =IF(3*(SUPUESTOS!B23*(1-SUPUESTOS!B25-SUPUESTOS!B26-SUPUESTOS!B27)-SUPUESTOS!B28-SUPUESTOS!B29)-SUPUESTOS!B35>=0,"✓ SÍ","✗ NO") -> ✓ SÍ
A15: 4 máquinas | C15: =4*(SUPUESTOS!B23*(1-SUPUESTOS!B25-SUPUESTOS!B26-SUPUESTOS!B27)-SUPUESTOS!B28-SUPUESTOS!B29)-SUPUESTOS!B35 -> 577 | E15: =(SUPUESTOS!B35/4+(SUPUESTOS!B28+SUPUESTOS!B29))/(1-SUPUESTOS!B25-SUPUESTOS!B26-SUPUESTOS!B27) -> 220.39474 | G15: =E15*SUPUESTOS!$B$4 -> 330592.11 | I15: =IF(4*(SUPUESTOS!B23*(1-SUPUESTOS!B25-SUPUESTOS!B26-SUPUESTOS!B27)-SUPUESTOS!B28-SUPUESTOS!B29)-SUPUESTOS!B35>=0,"✓ SÍ","✗ NO") -> ✓ SÍ
A16: 5 máquinas | C16: =5*(SUPUESTOS!B23*(1-SUPUESTOS!B25-SUPUESTOS!B26-SUPUESTOS!B27)-SUPUESTOS!B28-SUPUESTOS!B29)-SUPUESTOS!B35 -> 745 | E16: =(SUPUESTOS!B35/5+(SUPUESTOS!B28+SUPUESTOS!B29))/(1-SUPUESTOS!B25-SUPUESTOS!B26-SUPUESTOS!B27) -> 207.89474 | G16: =E16*SUPUESTOS!$B$4 -> 311842.11 | I16: =IF(5*(SUPUESTOS!B23*(1-SUPUESTOS!B25-SUPUESTOS!B26-SUPUESTOS!B27)-SUPUESTOS!B28-SUPUESTOS!B29)-SUPUESTOS!B35>=0,"✓ SÍ","✗ NO") -> ✓ SÍ
A17: 6 máquinas | C17: =6*(SUPUESTOS!B23*(1-SUPUESTOS!B25-SUPUESTOS!B26-SUPUESTOS!B27)-SUPUESTOS!B28-SUPUESTOS!B29)-SUPUESTOS!B35 -> 913 | E17: =(SUPUESTOS!B35/6+(SUPUESTOS!B28+SUPUESTOS!B29))/(1-SUPUESTOS!B25-SUPUESTOS!B26-SUPUESTOS!B27) -> 199.5614 | G17: =E17*SUPUESTOS!$B$4 -> 299342.11 | I17: =IF(6*(SUPUESTOS!B23*(1-SUPUESTOS!B25-SUPUESTOS!B26-SUPUESTOS!B27)-SUPUESTOS!B28-SUPUESTOS!B29)-SUPUESTOS!B35>=0,"✓ SÍ","✗ NO") -> ✓ SÍ
A18: 7 máquinas | C18: =7*(SUPUESTOS!B23*(1-SUPUESTOS!B25-SUPUESTOS!B26-SUPUESTOS!B27)-SUPUESTOS!B28-SUPUESTOS!B29)-SUPUESTOS!B35 -> 1081 | E18: =(SUPUESTOS!B35/7+(SUPUESTOS!B28+SUPUESTOS!B29))/(1-SUPUESTOS!B25-SUPUESTOS!B26-SUPUESTOS!B27) -> 193.60902 | G18: =E18*SUPUESTOS!$B$4 -> 290413.53 | I18: =IF(7*(SUPUESTOS!B23*(1-SUPUESTOS!B25-SUPUESTOS!B26-SUPUESTOS!B27)-SUPUESTOS!B28-SUPUESTOS!B29)-SUPUESTOS!B35>=0,"✓ SÍ","✗ NO") -> ✓ SÍ
A19: 8 máquinas | C19: =8*(SUPUESTOS!B23*(1-SUPUESTOS!B25-SUPUESTOS!B26-SUPUESTOS!B27)-SUPUESTOS!B28-SUPUESTOS!B29)-SUPUESTOS!B35 -> 1249 | E19: =(SUPUESTOS!B35/8+(SUPUESTOS!B28+SUPUESTOS!B29))/(1-SUPUESTOS!B25-SUPUESTOS!B26-SUPUESTOS!B27) -> 189.14474 | G19: =E19*SUPUESTOS!$B$4 -> 283717.11 | I19: =IF(8*(SUPUESTOS!B23*(1-SUPUESTOS!B25-SUPUESTOS!B26-SUPUESTOS!B27)-SUPUESTOS!B28-SUPUESTOS!B29)-SUPUESTOS!B35>=0,"✓ SÍ","✗ NO") -> ✓ SÍ
A21: Columnas VIOLETA = USD × TC (SUPUESTOS!B4). Rev. mínima en ARS es el ingreso en pesos que debe generar cada máquina para cubrir costos.

Sheet LEGAL
B1: VENDINS — CHECKLIST REGULATORIO & LEGAL — NEUQUÉN CAPITAL
B2: Trámite / Paso | C2: Organismo | D2: Costo Est. (USD) | E2: Plazo Est. | F2: Detalle / Notas
B3: FASE 0 — CONSTITUCIÓN SOCIETARIA
B4: 1. Solicitar denominación social (nombre VENDINS) | C4: Registro Público Neuquén | D4: ~30 | E4: 2-3 días | F4: Verificar disponibilidad. RPC Neuquén es provincial (NO IGJ nacional).
B5: 2. Redacción del contrato social SRL / SAS | C5: Escribanía / Estudio jurídico | D5: ~400 | E5: 3-5 días | F5: SAS (Ley 27.349): más rápida y barata para socio único. Objeto: 'comercialización mediante máquinas expendedoras automáticas'.
B6: 3. Inscripción en Registro Público Neuquén | C6: Registro Público de Comercio Neuquén | D6: ~400 | E6: 10-20 días | F6: Costo aprox. $450.000-600.000 ARS. Requiere contrato social, DNI, domicilio fiscal.
B7: 4. Obtención de CUIT (SRL/SAS) | C7: AFIP / ARCA — afip.gob.ar | D7: 0 | E7: 1-2 días online | F7: Clave fiscal nivel 3. Registrar domicilio fiscal en Neuquén Capital.
B8: FASE 1 — ALTA IMPOSITIVA NACIONAL (AFIP/ARCA)
B9: 5. Alta como Responsable Inscripto (IVA) | C9: AFIP / ARCA | D9: 0 | E9: Inmediato online | F9: Actividad: '4772 — Venta al por menor en comercios especializados'.
B10: 6. Alta en Impuesto a las Ganancias | C10: AFIP / ARCA | D10: 0 | E10: Inmediato online | F10: SRL/SAS tributa Ganancias sobre resultados. Período fiscal anual.
B11: 7. Inscripción Registro de Importadores/Exportadores | C11: AFIP / ARCA — Aduana | D11: 0 | E11: 3-10 días hábiles | F11: DDJJ 420/R vía Sistema Registral. Requisito para importar NCM 8476.
B12: FASE 2 — ALTA PROVINCIAL: INGRESOS BRUTOS NEUQUÉN
B13: 8. Inscripción en Ingresos Brutos — DPR Neuquén | C13: Dirección Provincial de Rentas (DPR) | D13: 0 | E13: 1-3 días online | F13: Formulario CD01 WEB en dprneuquen.gob.ar. Alícuota 2% (microempresa < $180M ARS).
B14: 9. Inscripción en SIFERE para declaraciones mensuales | C14: AFIP / ARCA + DPR | D14: 0 | E14: Inmediato | F14: DDJJ mensuales de Ingresos Brutos vía SIFERE.
B15: FASE 3 — HABILITACIÓN MUNICIPAL (MUNICIPIO DE NEUQUÉN)
B16: 10. Consulta previa: habilitación de operador vs. locador | C16: Dir. de Comercio Municipio Neuquén | D16: 0 | E16: 1 día consulta | F16: CRÍTICO: determinar si las máquinas en locales de terceros requieren habilitación propia. Tel.: (0299) 449-0300.
B17: 11. Solicitud de Licencia Comercial — Habilita Gratis | C17: Municipio de Neuquén Capital | D17: ~0 (Habilita Gratis) | E17: 15-30 días | F17: Programa municipal 2025: $0 para nuevas empresas + exenciones impositivas. Portal: neuquencapital.gov.ar.
B18: FASE 4 — IMPORTACIÓN DE MÁQUINAS (NCM 8476)
B19: 12. Verificar LINA (Licencia No Automática) NCM 8476.89.00 | C19: AFIP / ARCA Aduana | D19: 0 | E19: Consulta previa | F19: Arancel 14%. Verificar si aplica LINA antes de emitir orden de compra. Plazo LINA: 60-90 días adicionales si aplica.
B20: 13. Contratación de despachante de aduana | C20: CDA (Centro Despachantes Aduana) | D20: ~700 USD | E20: — | F20: cda.org.ar. Gestiona VUCEA, DJAI, SIMI y despacho completo.
B21: 14. Apertura carta de crédito / transferencia al proveedor | C21: Banco propio + BCRA | D21: Var. | E21: 3-10 días banco | F21: Montos >USD 10.000: declaración AFIP. Ver COSTOS_IMPO para totales en ARS.
B22: 15. Liquidación aduanera + pago de derechos + IVA | C22: Aduana Puerto Buenos Aires | D22: Ver COSTOS_IMPO | E22: 5-15 días hábiles | F22: Arancel 14% (no recuperable) + IVA 21% (recuperable) + IVA adic 10.5% (recuperable) + estadística 0.5%.
B23: 16. Flete interno Bs.As. → Neuquén (estimado ~USD 100/máq) | C23: Transportista regional | D23: ~300 USD (3 máqs) | E23: 3-5 días | F23: Cotizar con LAPA Cargas, Vía Bariloche Cargas o similar.
B24: FASE 5 — CONTRATOS CON LOCADORES
B25: 17. Modelo de contrato de ubicación de máquinas | C25: Asesor legal propio | D25: ~300-500 USD | E25: Único | F25: Cláusulas: plazo mínimo 12m, canon %, responsabilidad daños, exclusividad, resolución anticipada. Impuesto de Sellos: 14‰ del valor total del contrato.
B26: 18. Negociación con edificios corporativos petroleros | C26: RRHH / Administración edificio | D26: 0 | E26: Semanas | F26: YPF (Edificio Aura), TotalEnergies, Torre Trade, Pluspetrol. Presentar propuesta formal con estadísticas de uso.
B27: 19. Negociación con clínicas / hospitales privados | C27: Administración hospitalaria | D27: 0 | E27: Semanas | F27: Neuquén Med Center, Clínica Pasteur. Hospitales públicos (Castro Rendón) requieren CODINEU (Etapa 2+).
B28: 20. Negociación con Portal Patagonia Shopping | C28: Administración Portal Patagonia | D28: 0 | E28: Semanas | F28: Juan Julián Lastra 2400. Shoppings suelen pedir canon % + mínimo garantizado.
B29: FASE 6 — SANIDAD Y FARMACIA OTC (ETAPA 2)
B30: 21. Habilitación sanitaria ANMAT — productos envasados | C30: ANMAT / SENASA | D30: 0 | E30: Consulta | F30: Máquinas de alimentos envasados (RNE/RNPA del fabricante). Verificar requisitos por tipo de producto.
B31: 22. Consulta ANMAT y Colegio Farmacéuticos: OTC en vending | C31: ANMAT + Colegio Farmacéuticos NQN | D31: 0 | E31: Reunión | F31: Zona gris regulatoria. Alternativa recomendada: para-farmacia (preservativos, tests embarazo, alcohol gel) sin clasificación de medicamento.
